[
  {
    "id": "accessible-group-travel-ada-options-to-request",
    "slug": "accessible-group-travel-ada-options-to-request",
    "title": "Accessible Group Travel: ADA Options to Request",
    "excerpt": "Lock in ADA coaches, marshals, and signage before invites go out so every rider knows the plan.",
    "content": "It is easy to romanticize accessible group travel: ada options to request, but Inclusive charters succeed when mobility, sensory, and caregiver details are scripted weeks before doors open and every guest sees their needs acknowledged. Bus2Ride treats every transport storyboard as a live operations document where each promise has an owner and a timestamp. We convert the directional keywords you keep repeating—Accessible, Group, Travel, Ada—into routing guardrails, staffing ratios, and guest communications. That discipline keeps stakeholders aligned even when celebrity handlers, weather alerts, or late sponsor asks enter the chat at the last minute. By defining success through rider outcomes instead of vehicle specs, the rest of the planning stack becomes calmer and measurably more resilient. The goal is a weekend or single-night move that still feels effortless to guests while your logistics brain knows every variable has a backup.\n\nPlanning begins weeks upstream with discovery calls, forms, and scouting drives anchored around power wheelchair manifests, caregiver RSVP follow ups, timed practice fittings. We map each traveler persona against the run of show so no one is surprised by attire changes, ADA requirements, or last minute VIP arrivals. Our producers draft layered itineraries that explain who greets whom, which curb is primary versus fallback, and what copy needs to be printed for signage. That documentation lets executives, wedding planners, campus staff, or brand teams sign off quickly because they can see the downstream effect of every choice. We also log no-go rules—the songs that must play, the neighborhoods to avoid, the shots the photographer is chasing—so host energy stays protected. When the planning stack reaches that clarity, even complex ADA, accessibility, group travel programs feel approachable.\n\nLogistics rehearsal focuses on curb cuts, freight elevators, protected staging lanes with human marshals and the unglamorous tasks that actually preserve timelines. We confirm permits, credential needs, and staging pads with photos, measurements, and contacts so the driver handshake is more than a blind guess. Dispatch receives scenario scripts for weather, traffic gridlock, or celebrity security tweaks, and we mirror those scripts for the host team. Every loop has a dwell budget, fuel plan, restroom strategy, and spare vehicle logic documented in plain English. Because our on-site captains have direct radio or WhatsApp channels with chauffeurs, we can pulse information before a delay becomes a stall. That muscle memory turns potential chaos into small course corrections riders never notice.\n\nAmenities are curated intentionally instead of sprinkled randomly, with the spotlight on modern lifts, spare securements, sensory dimming light scenes. We compare rider avatars against cabin layouts to decide where hydration stations, photo props, vow cards, or merch drops should live. Hosts receive a diagram that labels every comfort touch so they know what to hype on the mic, what to protect from overuse, and when to refresh each zone. When a vehicle swap happens, our amenity trunks and digital signage kits move too, which keeps the vibe consistent. We also script how chauffeurs or onboard concierges introduce the upgrades so the spend feels premium rather than gimmicky. Done right, the amenities quietly accelerate boarding, encourage social sharing, and keep the story cohesive from stop to stop.\n\nBudget modeling is transparent because we tie every dollar to a measurable constraint, especially around standby ADA shuttles, mobility tech retainers, buffer dwell time blocks. Finance leaders see the decision matrix that compares doing nothing, DIY attempts, or hiring the operator to handle it turnkey. We highlight the costs of failure—injury claims, overtime spirals, missed sponsorship impressions—so approvals feel logical, not emotional. During build-out we log which lines are flexible and which are sacred, making it easier to pivot if the group size or routing changes. Deposits, milestone payments, and gratuity plans are stored in a single tracker to prevent the dreaded text chain of “who still owes what.” With that clarity, stakeholders stay calm even when the scope evolves because they understand the tradeoffs.\n\nExperience design pulls everything together with quiet cabins, plain language announcements, multi format recaps that spotlight wins so guests feel guided instead of herded. We coach emcees, chauffeurs, and onboard crew on language that is inclusive, celebratory, and sensitive to the group’s culture. Live comms go out through SMS, WhatsApp, and QR-enabled microsites so riders always know where to stand, what is next, and who to text for help. Our media team stages photo or video beats that match the narrative arc, whether that is a reveal moment, a toast, or a chill reset. Post-trip surveys gather candid feedback plus testimonials the client can reuse internally, giving the transportation line item long-tail value. When riders feel seen at every touchpoint, the charter becomes part of the story instead of just a shuttle.\n\nIf you want this level of rigor for your own accessible group travel: ada options to request, tap the Bus2Ride concierge team and we will adapt the playbook to your city. We can collaborate directly with venues, production partners, hotels, or corporate travel managers and share our dashboards so everyone watches the same KPIs. Send a quick brief to info@bus2ride.com or call (888) 535-2566, and we will workshop route ideas, budgets, and backup plans in the first conversation. From there we lock in the exact fleet mix, staffing model, and amenity set that makes your brand, family, or fan base feel unstoppable.",
    "wordCount": 881,
    "thumbnail_url": "blog/Ada Accesibility.jpg",
    "published_at": "2025-01-05T12:00:00Z",
    "created_at": "2025-01-05T12:00:00Z",
    "updated_at": "2025-01-05T12:00:00Z",
    "keywords": [
      "ADA",
      "accessibility",
      "group travel"
    ],
    "introHook": "Inclusive charters succeed when mobility, sensory, and caregiver details are scripted weeks before doors open and every guest sees their needs acknowledged.",
    "planningFocus": "power wheelchair manifests, caregiver RSVP follow ups, timed practice fittings",
    "logisticsFocus": "curb cuts, freight elevators, protected staging lanes with human marshals",
    "amenitiesFocus": "modern lifts, spare securements, sensory dimming light scenes",
    "budgetFocus": "standby ADA shuttles, mobility tech retainers, buffer dwell time blocks",
    "experienceFocus": "quiet cabins, plain language announcements, multi format recaps that spotlight wins"
  },
  {
    "id": "add-ons-that-are-actually-worth-it",
    "slug": "add-ons-that-are-actually-worth-it",
    "title": "Add-Ons That Are Actually Worth It",
    "excerpt": "Retire gimmick upgrades and fund amenities that measurably improve comfort, dwell speed, and photo moments.",
    "content": "It is easy to romanticize add-ons that are actually worth it, but We audited two hundred charters to rank the extras riders recall once playlists fade and phones go back in pockets. Bus2Ride treats every transport storyboard as a live operations document where each promise has an owner and a timestamp. We convert the directional keywords you keep repeating—Add, Ons, That, Are—into routing guardrails, staffing ratios, and guest communications. That discipline keeps stakeholders aligned even when celebrity handlers, weather alerts, or late sponsor asks enter the chat at the last minute. By defining success through rider outcomes instead of vehicle specs, the rest of the planning stack becomes calmer and measurably more resilient. The goal is a weekend or single-night move that still feels effortless to guests while your logistics brain knows every variable has a backup.\n\nPlanning begins weeks upstream with discovery calls, forms, and scouting drives anchored around stacked service tiers, rider research calls, pre trip amenity scripting. We map each traveler persona against the run of show so no one is surprised by attire changes, ADA requirements, or last minute VIP arrivals. Our producers draft layered itineraries that explain who greets whom, which curb is primary versus fallback, and what copy needs to be printed for signage. That documentation lets executives, wedding planners, campus staff, or brand teams sign off quickly because they can see the downstream effect of every choice. We also log no-go rules—the songs that must play, the neighborhoods to avoid, the shots the photographer is chasing—so host energy stays protected. When the planning stack reaches that clarity, even complex amenities, budget, experience programs feel approachable.\n\nLogistics rehearsal focuses on ownership charts for stocking, photo ready staging, cooler placement that guides flow and the unglamorous tasks that actually preserve timelines. We confirm permits, credential needs, and staging pads with photos, measurements, and contacts so the driver handshake is more than a blind guess. Dispatch receives scenario scripts for weather, traffic gridlock, or celebrity security tweaks, and we mirror those scripts for the host team. Every loop has a dwell budget, fuel plan, restroom strategy, and spare vehicle logic documented in plain English. Because our on-site captains have direct radio or WhatsApp channels with chauffeurs, we can pulse information before a delay becomes a stall. That muscle memory turns potential chaos into small course corrections riders never notice.\n\nAmenities are curated intentionally instead of sprinkled randomly, with the spotlight on hydration carts, climate boosters, branded welcome notes that match livery. We compare rider avatars against cabin layouts to decide where hydration stations, photo props, vow cards, or merch drops should live. Hosts receive a diagram that labels every comfort touch so they know what to hype on the mic, what to protect from overuse, and when to refresh each zone. When a vehicle swap happens, our amenity trunks and digital signage kits move too, which keeps the vibe consistent. We also script how chauffeurs or onboard concierges introduce the upgrades so the spend feels premium rather than gimmicky. Done right, the amenities quietly accelerate boarding, encourage social sharing, and keep the story cohesive from stop to stop.\n\nBudget modeling is transparent because we tie every dollar to a measurable constraint, especially around tie spend to KPIs and compare turnkey vendor bundles versus DIY costs. Finance leaders see the decision matrix that compares doing nothing, DIY attempts, or hiring the operator to handle it turnkey. We highlight the costs of failure—injury claims, overtime spirals, missed sponsorship impressions—so approvals feel logical, not emotional. During build-out we log which lines are flexible and which are sacred, making it easier to pivot if the group size or routing changes. Deposits, milestone payments, and gratuity plans are stored in a single tracker to prevent the dreaded text chain of “who still owes what.” With that clarity, stakeholders stay calm even when the scope evolves because they understand the tradeoffs.\n\nExperience design pulls everything together with onboard hosts narrating perks, tactile keepsakes, next day media drops so guests feel guided instead of herded. We coach emcees, chauffeurs, and onboard crew on language that is inclusive, celebratory, and sensitive to the group’s culture. Live comms go out through SMS, WhatsApp, and QR-enabled microsites so riders always know where to stand, what is next, and who to text for help. Our media team stages photo or video beats that match the narrative arc, whether that is a reveal moment, a toast, or a chill reset. Post-trip surveys gather candid feedback plus testimonials the client can reuse internally, giving the transportation line item long-tail value. When riders feel seen at every touchpoint, the charter becomes part of the story instead of just a shuttle.\n\nIf you want this level of rigor for your own add-ons that are actually worth it, tap the Bus2Ride concierge team and we will adapt the playbook to your city. We can collaborate directly with venues, production partners, hotels, or corporate travel managers and share our dashboards so everyone watches the same KPIs. Send a quick brief to info@bus2ride.com or call (888) 535-2566, and we will workshop route ideas, budgets, and backup plans in the first conversation. From there we lock in the exact fleet mix, staffing model, and amenity set that makes your brand, family, or fan base feel unstoppable.",
    "wordCount": 881,
    "thumbnail_url": "blog/Add Ons.jpg",
    "published_at": "2025-01-06T12:00:00Z",
    "created_at": "2025-01-06T12:00:00Z",
    "updated_at": "2025-01-06T12:00:00Z",
    "keywords": [
      "amenities",
      "budget",
      "experience"
    ],
    "introHook": "We audited two hundred charters to rank the extras riders recall once playlists fade and phones go back in pockets.",
    "planningFocus": "stacked service tiers, rider research calls, pre trip amenity scripting",
    "logisticsFocus": "ownership charts for stocking, photo ready staging, cooler placement that guides flow",
    "amenitiesFocus": "hydration carts, climate boosters, branded welcome notes that match livery",
    "budgetFocus": "tie spend to KPIs and compare turnkey vendor bundles versus DIY costs",
    "experienceFocus": "onboard hosts narrating perks, tactile keepsakes, next day media drops"
  },
  {
    "id": "airport-transfers-black-car-vs-suv-which-should-you-book",
    "slug": "airport-transfers-black-car-vs-suv-which-should-you-book",
    "title": "Airport Transfers: Black Car vs SUV",
    "excerpt": "Choose the right airport vehicle class by balancing luggage realities, meet and greet optics, and curb space limitations.",
    "content": "It is easy to romanticize airport transfers: black car vs suv, but Arrivals coordinators juggle jet bridge texts, customs delays, and baggage carts, so the car you assign must match the real payload. Bus2Ride treats every transport storyboard as a live operations document where each promise has an owner and a timestamp. We convert the directional keywords you keep repeating—Airport, Transfers, Black, Car—into routing guardrails, staffing ratios, and guest communications. That discipline keeps stakeholders aligned even when celebrity handlers, weather alerts, or late sponsor asks enter the chat at the last minute. By defining success through rider outcomes instead of vehicle specs, the rest of the planning stack becomes calmer and measurably more resilient. The goal is a weekend or single-night move that still feels effortless to guests while your logistics brain knows every variable has a backup.\n\nPlanning begins weeks upstream with discovery calls, forms, and scouting drives anchored around flight manifest cross checks, buffer scheduling, greeter sign playbooks. We map each traveler persona against the run of show so no one is surprised by attire changes, ADA requirements, or last minute VIP arrivals. Our producers draft layered itineraries that explain who greets whom, which curb is primary versus fallback, and what copy needs to be printed for signage. That documentation lets executives, wedding planners, campus staff, or brand teams sign off quickly because they can see the downstream effect of every choice. We also log no-go rules—the songs that must play, the neighborhoods to avoid, the shots the photographer is chasing—so host energy stays protected. When the planning stack reaches that clarity, even complex airport, black car, SUV programs feel approachable.\n\nLogistics rehearsal focuses on curb control, TSA wait monitoring, parallel staging for delayed flights and the unglamorous tasks that actually preserve timelines. We confirm permits, credential needs, and staging pads with photos, measurements, and contacts so the driver handshake is more than a blind guess. Dispatch receives scenario scripts for weather, traffic gridlock, or celebrity security tweaks, and we mirror those scripts for the host team. Every loop has a dwell budget, fuel plan, restroom strategy, and spare vehicle logic documented in plain English. Because our on-site captains have direct radio or WhatsApp channels with chauffeurs, we can pulse information before a delay becomes a stall. That muscle memory turns potential chaos into small course corrections riders never notice.\n\nAmenities are curated intentionally instead of sprinkled randomly, with the spotlight on luggage nets, chilled towels, seat pocket route cards. We compare rider avatars against cabin layouts to decide where hydration stations, photo props, vow cards, or merch drops should live. Hosts receive a diagram that labels every comfort touch so they know what to hype on the mic, what to protect from overuse, and when to refresh each zone. When a vehicle swap happens, our amenity trunks and digital signage kits move too, which keeps the vibe consistent. We also script how chauffeurs or onboard concierges introduce the upgrades so the spend feels premium rather than gimmicky. Done right, the amenities quietly accelerate boarding, encourage social sharing, and keep the story cohesive from stop to stop.\n\nBudget modeling is transparent because we tie every dollar to a measurable constraint, especially around stack pricing ladders, surge protections, blended hourly blocks for rolling ETAs. Finance leaders see the decision matrix that compares doing nothing, DIY attempts, or hiring the operator to handle it turnkey. We highlight the costs of failure—injury claims, overtime spirals, missed sponsorship impressions—so approvals feel logical, not emotional. During build-out we log which lines are flexible and which are sacred, making it easier to pivot if the group size or routing changes. Deposits, milestone payments, and gratuity plans are stored in a single tracker to prevent the dreaded text chain of “who still owes what.” With that clarity, stakeholders stay calm even when the scope evolves because they understand the tradeoffs.\n\nExperience design pulls everything together with VIP escorts, WhatsApp tracking links, recap emails that confirm every tail number landed smoothly so guests feel guided instead of herded. We coach emcees, chauffeurs, and onboard crew on language that is inclusive, celebratory, and sensitive to the group’s culture. Live comms go out through SMS, WhatsApp, and QR-enabled microsites so riders always know where to stand, what is next, and who to text for help. Our media team stages photo or video beats that match the narrative arc, whether that is a reveal moment, a toast, or a chill reset. Post-trip surveys gather candid feedback plus testimonials the client can reuse internally, giving the transportation line item long-tail value. When riders feel seen at every touchpoint, the charter becomes part of the story instead of just a shuttle.\n\nIf you want this level of rigor for your own airport transfers: black car vs suv, tap the Bus2Ride concierge team and we will adapt the playbook to your city. We can collaborate directly with venues, production partners, hotels, or corporate travel managers and share our dashboards so everyone watches the same KPIs. Send a quick brief to info@bus2ride.com or call (888) 535-2566, and we will workshop route ideas, budgets, and backup plans in the first conversation. From there we lock in the exact fleet mix, staffing model, and amenity set that makes your brand, family, or fan base feel unstoppable.",
    "wordCount": 881,
    "thumbnail_url": "blog/airport transfers.jpg",
    "published_at": "2025-01-07T12:00:00Z",
    "created_at": "2025-01-07T12:00:00Z",
    "updated_at": "2025-01-07T12:00:00Z",
    "keywords": [
      "airport",
      "black car",
      "SUV"
    ],
    "introHook": "Arrivals coordinators juggle jet bridge texts, customs delays, and baggage carts, so the car you assign must match the real payload.",
    "planningFocus": "flight manifest cross checks, buffer scheduling, greeter sign playbooks",
    "logisticsFocus": "curb control, TSA wait monitoring, parallel staging for delayed flights",
    "amenitiesFocus": "luggage nets, chilled towels, seat pocket route cards",
    "budgetFocus": "stack pricing ladders, surge protections, blended hourly blocks for rolling ETAs",
    "experienceFocus": "VIP escorts, WhatsApp tracking links, recap emails that confirm every tail number landed smoothly"
  },
  {
    "id": "city-guide-best-night-out-routes-by-party-bus",
    "slug": "city-guide-best-night-out-routes-by-party-bus",
    "title": "City Guide: Best Night-Out Routes by Party Bus",
    "excerpt": "Thread together nightlife neighborhoods with staging pads, photo stops, and restroom access so the night feels seamless.",
    "content": "It is easy to romanticize city guide: best night-out routes by party bus, but The difference between a chaotic crawl and a cinematic night is route sequencing that respects capacity, security lines, and mood arcs. Bus2Ride treats every transport storyboard as a live operations document where each promise has an owner and a timestamp. We convert the directional keywords you keep repeating—City, Guide, Best, Night—into routing guardrails, staffing ratios, and guest communications. That discipline keeps stakeholders aligned even when celebrity handlers, weather alerts, or late sponsor asks enter the chat at the last minute. By defining success through rider outcomes instead of vehicle specs, the rest of the planning stack becomes calmer and measurably more resilient. The goal is a weekend or single-night move that still feels effortless to guests while your logistics brain knows every variable has a backup.\n\nPlanning begins weeks upstream with discovery calls, forms, and scouting drives anchored around venue scouting walks, host scripts, pace layering between hype and recharge moments. We map each traveler persona against the run of show so no one is surprised by attire changes, ADA requirements, or last minute VIP arrivals. Our producers draft layered itineraries that explain who greets whom, which curb is primary versus fallback, and what copy needs to be printed for signage. That documentation lets executives, wedding planners, campus staff, or brand teams sign off quickly because they can see the downstream effect of every choice. We also log no-go rules—the songs that must play, the neighborhoods to avoid, the shots the photographer is chasing—so host energy stays protected. When the planning stack reaches that clarity, even complex nightlife, party bus, routes programs feel approachable.\n\nLogistics rehearsal focuses on loop timing, alley staging permissions, marshals clearing curb fans and the unglamorous tasks that actually preserve timelines. We confirm permits, credential needs, and staging pads with photos, measurements, and contacts so the driver handshake is more than a blind guess. Dispatch receives scenario scripts for weather, traffic gridlock, or celebrity security tweaks, and we mirror those scripts for the host team. Every loop has a dwell budget, fuel plan, restroom strategy, and spare vehicle logic documented in plain English. Because our on-site captains have direct radio or WhatsApp channels with chauffeurs, we can pulse information before a delay becomes a stall. That muscle memory turns potential chaos into small course corrections riders never notice.\n\nAmenities are curated intentionally instead of sprinkled randomly, with the spotlight on charging bundles, DJ ready inputs, scent and lighting presets per stop. We compare rider avatars against cabin layouts to decide where hydration stations, photo props, vow cards, or merch drops should live. Hosts receive a diagram that labels every comfort touch so they know what to hype on the mic, what to protect from overuse, and when to refresh each zone. When a vehicle swap happens, our amenity trunks and digital signage kits move too, which keeps the vibe consistent. We also script how chauffeurs or onboard concierges introduce the upgrades so the spend feels premium rather than gimmicky. Done right, the amenities quietly accelerate boarding, encourage social sharing, and keep the story cohesive from stop to stop.\n\nBudget modeling is transparent because we tie every dollar to a measurable constraint, especially around bundle cover charges, tipping pools, security detail add ons to avoid last minute ATM runs. Finance leaders see the decision matrix that compares doing nothing, DIY attempts, or hiring the operator to handle it turnkey. We highlight the costs of failure—injury claims, overtime spirals, missed sponsorship impressions—so approvals feel logical, not emotional. During build-out we log which lines are flexible and which are sacred, making it easier to pivot if the group size or routing changes. Deposits, milestone payments, and gratuity plans are stored in a single tracker to prevent the dreaded text chain of “who still owes what.” With that clarity, stakeholders stay calm even when the scope evolves because they understand the tradeoffs.\n\nExperience design pulls everything together with photo captains, geo tagged recap maps, morning-after highlight reels so guests feel guided instead of herded. We coach emcees, chauffeurs, and onboard crew on language that is inclusive, celebratory, and sensitive to the group’s culture. Live comms go out through SMS, WhatsApp, and QR-enabled microsites so riders always know where to stand, what is next, and who to text for help. Our media team stages photo or video beats that match the narrative arc, whether that is a reveal moment, a toast, or a chill reset. Post-trip surveys gather candid feedback plus testimonials the client can reuse internally, giving the transportation line item long-tail value. When riders feel seen at every touchpoint, the charter becomes part of the story instead of just a shuttle.\n\nIf you want this level of rigor for your own city guide: best night-out routes by party bus, tap the Bus2Ride concierge team and we will adapt the playbook to your city. We can collaborate directly with venues, production partners, hotels, or corporate travel managers and share our dashboards so everyone watches the same KPIs. Send a quick brief to info@bus2ride.com or call (888) 535-2566, and we will workshop route ideas, budgets, and backup plans in the first conversation. From there we lock in the exact fleet mix, staffing model, and amenity set that makes your brand, family, or fan base feel unstoppable.",
    "wordCount": 889,
    "thumbnail_url": "blog/City Guide.jpg",
    "published_at": "2025-01-08T12:00:00Z",
    "created_at": "2025-01-08T12:00:00Z",
    "updated_at": "2025-01-08T12:00:00Z",
    "keywords": [
      "nightlife",
      "party bus",
      "routes"
    ],
    "introHook": "The difference between a chaotic crawl and a cinematic night is route sequencing that respects capacity, security lines, and mood arcs.",
    "planningFocus": "venue scouting walks, host scripts, pace layering between hype and recharge moments",
    "logisticsFocus": "loop timing, alley staging permissions, marshals clearing curb fans",
    "amenitiesFocus": "charging bundles, DJ ready inputs, scent and lighting presets per stop",
    "budgetFocus": "bundle cover charges, tipping pools, security detail add ons to avoid last minute ATM runs",
    "experienceFocus": "photo captains, geo tagged recap maps, morning-after highlight reels"
  },
  {
    "id": "the-ultimate-bachelor-bachelorette-party-bus-playbook",
    "slug": "the-ultimate-bachelor-bachelorette-party-bus-playbook",
    "title": "Bachelor & Bachelorette Party Bus Playbook",
    "excerpt": "Design rowdy but safe itineraries with personal touches, hydration cycles, and backup plans for every wildcard friend.",
    "content": "It is easy to romanticize bachelor & bachelorette party bus playbook, but Wedding parties crave spectacle but still need seat belts, pacing, and a point person who can say no when needed. Bus2Ride treats every transport storyboard as a live operations document where each promise has an owner and a timestamp. We convert the directional keywords you keep repeating—Ultimate, Bachelor, Bachelorette, Party—into routing guardrails, staffing ratios, and guest communications. That discipline keeps stakeholders aligned even when celebrity handlers, weather alerts, or late sponsor asks enter the chat at the last minute. By defining success through rider outcomes instead of vehicle specs, the rest of the planning stack becomes calmer and measurably more resilient. The goal is a weekend or single-night move that still feels effortless to guests while your logistics brain knows every variable has a backup.\n\nPlanning begins weeks upstream with discovery calls, forms, and scouting drives anchored around role assignments for hosts, bridal concierge check ins, milestone reveals. We map each traveler persona against the run of show so no one is surprised by attire changes, ADA requirements, or last minute VIP arrivals. Our producers draft layered itineraries that explain who greets whom, which curb is primary versus fallback, and what copy needs to be printed for signage. That documentation lets executives, wedding planners, campus staff, or brand teams sign off quickly because they can see the downstream effect of every choice. We also log no-go rules—the songs that must play, the neighborhoods to avoid, the shots the photographer is chasing—so host energy stays protected. When the planning stack reaches that clarity, even complex bachelor, bachelorette, party bus programs feel approachable.\n\nLogistics rehearsal focuses on hotel bag drops, wristband distribution, surprise guest arrival timing and the unglamorous tasks that actually preserve timelines. We confirm permits, credential needs, and staging pads with photos, measurements, and contacts so the driver handshake is more than a blind guess. Dispatch receives scenario scripts for weather, traffic gridlock, or celebrity security tweaks, and we mirror those scripts for the host team. Every loop has a dwell budget, fuel plan, restroom strategy, and spare vehicle logic documented in plain English. Because our on-site captains have direct radio or WhatsApp channels with chauffeurs, we can pulse information before a delay becomes a stall. That muscle memory turns potential chaos into small course corrections riders never notice.\n\nAmenities are curated intentionally instead of sprinkled randomly, with the spotlight on custom playlists, monogrammed glassware, recovery kits stocked with electrolytes. We compare rider avatars against cabin layouts to decide where hydration stations, photo props, vow cards, or merch drops should live. Hosts receive a diagram that labels every comfort touch so they know what to hype on the mic, what to protect from overuse, and when to refresh each zone. When a vehicle swap happens, our amenity trunks and digital signage kits move too, which keeps the vibe consistent. We also script how chauffeurs or onboard concierges introduce the upgrades so the spend feels premium rather than gimmicky. Done right, the amenities quietly accelerate boarding, encourage social sharing, and keep the story cohesive from stop to stop.\n\nBudget modeling is transparent because we tie every dollar to a measurable constraint, especially around shared payment links, sponsor buy ins, contingency fund for last second upgrades. Finance leaders see the decision matrix that compares doing nothing, DIY attempts, or hiring the operator to handle it turnkey. We highlight the costs of failure—injury claims, overtime spirals, missed sponsorship impressions—so approvals feel logical, not emotional. During build-out we log which lines are flexible and which are sacred, making it easier to pivot if the group size or routing changes. Deposits, milestone payments, and gratuity plans are stored in a single tracker to prevent the dreaded text chain of “who still owes what.” With that clarity, stakeholders stay calm even when the scope evolves because they understand the tradeoffs.\n\nExperience design pulls everything together with toast scripts, disposable camera prompts, private gallery delivery the next day so guests feel guided instead of herded. We coach emcees, chauffeurs, and onboard crew on language that is inclusive, celebratory, and sensitive to the group’s culture. Live comms go out through SMS, WhatsApp, and QR-enabled microsites so riders always know where to stand, what is next, and who to text for help. Our media team stages photo or video beats that match the narrative arc, whether that is a reveal moment, a toast, or a chill reset. Post-trip surveys gather candid feedback plus testimonials the client can reuse internally, giving the transportation line item long-tail value. When riders feel seen at every touchpoint, the charter becomes part of the story instead of just a shuttle.\n\nIf you want this level of rigor for your own bachelor & bachelorette party bus playbook, tap the Bus2Ride concierge team and we will adapt the playbook to your city. We can collaborate directly with venues, production partners, hotels, or corporate travel managers and share our dashboards so everyone watches the same KPIs. Send a quick brief to info@bus2ride.com or call (888) 535-2566, and we will workshop route ideas, budgets, and backup plans in the first conversation. From there we lock in the exact fleet mix, staffing model, and amenity set that makes your brand, family, or fan base feel unstoppable.",
    "wordCount": 879,
    "thumbnail_url": "blog/Bachelor Bachelorette.jpg",
    "published_at": "2025-01-09T12:00:00Z",
    "created_at": "2025-01-09T12:00:00Z",
    "updated_at": "2025-01-09T12:00:00Z",
    "keywords": [
      "bachelor",
      "bachelorette",
      "party bus"
    ],
    "introHook": "Wedding parties crave spectacle but still need seat belts, pacing, and a point person who can say no when needed.",
    "planningFocus": "role assignments for hosts, bridal concierge check ins, milestone reveals",
    "logisticsFocus": "hotel bag drops, wristband distribution, surprise guest arrival timing",
    "amenitiesFocus": "custom playlists, monogrammed glassware, recovery kits stocked with electrolytes",
    "budgetFocus": "shared payment links, sponsor buy ins, contingency fund for last second upgrades",
    "experienceFocus": "toast scripts, disposable camera prompts, private gallery delivery the next day"
  },
  {
    "id": "wine-brewery-tours-how-to-plan-a-perfect-tasting-day",
    "slug": "wine-brewery-tours-how-to-plan-a-perfect-tasting-day",
    "title": "Wine & Brewery Tours: Plan a Perfect Tasting Day",
    "excerpt": "Balance pours with pacing, farm roads, and food pairings so nobody naps through the finale.",
    "content": "It is easy to romanticize wine & brewery tours: plan a perfect tasting day, but Rural tasting circuits reward planners who confirm harvest closures, crush season traffic, and restroom counts in advance. Bus2Ride treats every transport storyboard as a live operations document where each promise has an owner and a timestamp. We convert the directional keywords you keep repeating—Wine, Brewery, Tours, Plan—into routing guardrails, staffing ratios, and guest communications. That discipline keeps stakeholders aligned even when celebrity handlers, weather alerts, or late sponsor asks enter the chat at the last minute. By defining success through rider outcomes instead of vehicle specs, the rest of the planning stack becomes calmer and measurably more resilient. The goal is a weekend or single-night move that still feels effortless to guests while your logistics brain knows every variable has a backup.\n\nPlanning begins weeks upstream with discovery calls, forms, and scouting drives anchored around RSVP taxonomy by palate, annotated itineraries, tasting card packets. We map each traveler persona against the run of show so no one is surprised by attire changes, ADA requirements, or last minute VIP arrivals. Our producers draft layered itineraries that explain who greets whom, which curb is primary versus fallback, and what copy needs to be printed for signage. That documentation lets executives, wedding planners, campus staff, or brand teams sign off quickly because they can see the downstream effect of every choice. We also log no-go rules—the songs that must play, the neighborhoods to avoid, the shots the photographer is chasing—so host energy stays protected. When the planning stack reaches that clarity, even complex wine tour, brewery, tasting programs feel approachable.\n\nLogistics rehearsal focuses on vineyard access roads, driver meal plans, cold chain for take-home bottles and the unglamorous tasks that actually preserve timelines. We confirm permits, credential needs, and staging pads with photos, measurements, and contacts so the driver handshake is more than a blind guess. Dispatch receives scenario scripts for weather, traffic gridlock, or celebrity security tweaks, and we mirror those scripts for the host team. Every loop has a dwell budget, fuel plan, restroom strategy, and spare vehicle logic documented in plain English. Because our on-site captains have direct radio or WhatsApp channels with chauffeurs, we can pulse information before a delay becomes a stall. That muscle memory turns potential chaos into small course corrections riders never notice.\n\nAmenities are curated intentionally instead of sprinkled randomly, with the spotlight on glass racks, charcuterie staging, under-seat coolers with ice blankets. We compare rider avatars against cabin layouts to decide where hydration stations, photo props, vow cards, or merch drops should live. Hosts receive a diagram that labels every comfort touch so they know what to hype on the mic, what to protect from overuse, and when to refresh each zone. When a vehicle swap happens, our amenity trunks and digital signage kits move too, which keeps the vibe consistent. We also script how chauffeurs or onboard concierges introduce the upgrades so the spend feels premium rather than gimmicky. Done right, the amenities quietly accelerate boarding, encourage social sharing, and keep the story cohesive from stop to stop.\n\nBudget modeling is transparent because we tie every dollar to a measurable constraint, especially around per-person tasting credits, gratuity ladders, insurance for pallet pickups. Finance leaders see the decision matrix that compares doing nothing, DIY attempts, or hiring the operator to handle it turnkey. We highlight the costs of failure—injury claims, overtime spirals, missed sponsorship impressions—so approvals feel logical, not emotional. During build-out we log which lines are flexible and which are sacred, making it easier to pivot if the group size or routing changes. Deposits, milestone payments, and gratuity plans are stored in a single tracker to prevent the dreaded text chain of “who still owes what.” With that clarity, stakeholders stay calm even when the scope evolves because they understand the tradeoffs.\n\nExperience design pulls everything together with storytelling hosts, pairing notes, digital field guides sent post trip so guests feel guided instead of herded. We coach emcees, chauffeurs, and onboard crew on language that is inclusive, celebratory, and sensitive to the group’s culture. Live comms go out through SMS, WhatsApp, and QR-enabled microsites so riders always know where to stand, what is next, and who to text for help. Our media team stages photo or video beats that match the narrative arc, whether that is a reveal moment, a toast, or a chill reset. Post-trip surveys gather candid feedback plus testimonials the client can reuse internally, giving the transportation line item long-tail value. When riders feel seen at every touchpoint, the charter becomes part of the story instead of just a shuttle.\n\nIf you want this level of rigor for your own wine & brewery tours: plan a perfect tasting day, tap the Bus2Ride concierge team and we will adapt the playbook to your city. We can collaborate directly with venues, production partners, hotels, or corporate travel managers and share our dashboards so everyone watches the same KPIs. Send a quick brief to info@bus2ride.com or call (888) 535-2566, and we will workshop route ideas, budgets, and backup plans in the first conversation. From there we lock in the exact fleet mix, staffing model, and amenity set that makes your brand, family, or fan base feel unstoppable.",
    "wordCount": 879,
    "thumbnail_url": "blog/Wine tour.jpg",
    "published_at": "2025-01-10T12:00:00Z",
    "created_at": "2025-01-10T12:00:00Z",
    "updated_at": "2025-01-10T12:00:00Z",
    "keywords": [
      "wine tour",
      "brewery",
      "tasting"
    ],
    "introHook": "Rural tasting circuits reward planners who confirm harvest closures, crush season traffic, and restroom counts in advance.",
    "planningFocus": "RSVP taxonomy by palate, annotated itineraries, tasting card packets",
    "logisticsFocus": "vineyard access roads, driver meal plans, cold chain for take-home bottles",
    "amenitiesFocus": "glass racks, charcuterie staging, under-seat coolers with ice blankets",
    "budgetFocus": "per-person tasting credits, gratuity ladders, insurance for pallet pickups",
    "experienceFocus": "storytelling hosts, pairing notes, digital field guides sent post trip"
  },
  {
    "id": "byob-on-party-buses-rules-coolers-and-no-glass-tips",
    "slug": "byob-on-party-buses-rules-coolers-and-no-glass-tips",
    "title": "BYOB on Party Buses: Rules, Coolers, and No-Glass Tips",
    "excerpt": "Keep the BYOB vibe fun without flirting with citations, spills, or broken glass on the dance floor.",
    "content": "It is easy to romanticize byob on party buses: rules, coolers, and no-glass tips, but Most municipalities allow rider supplied beverages, but only if you choreograph paperwork, containers, and host scripts. Bus2Ride treats every transport storyboard as a live operations document where each promise has an owner and a timestamp. We convert the directional keywords you keep repeating—Byob, Party, Buses, Rules—into routing guardrails, staffing ratios, and guest communications. That discipline keeps stakeholders aligned even when celebrity handlers, weather alerts, or late sponsor asks enter the chat at the last minute. By defining success through rider outcomes instead of vehicle specs, the rest of the planning stack becomes calmer and measurably more resilient. The goal is a weekend or single-night move that still feels effortless to guests while your logistics brain knows every variable has a backup.\n\nPlanning begins weeks upstream with discovery calls, forms, and scouting drives anchored around permit checks, rider waivers, captain assignments for cooler resets. We map each traveler persona against the run of show so no one is surprised by attire changes, ADA requirements, or last minute VIP arrivals. Our producers draft layered itineraries that explain who greets whom, which curb is primary versus fallback, and what copy needs to be printed for signage. That documentation lets executives, wedding planners, campus staff, or brand teams sign off quickly because they can see the downstream effect of every choice. We also log no-go rules—the songs that must play, the neighborhoods to avoid, the shots the photographer is chasing—so host energy stays protected. When the planning stack reaches that clarity, even complex BYOB, party bus, safety programs feel approachable.\n\nLogistics rehearsal focuses on ice swaps at fuel stops, trash rotations, sealed glass drop bins with locks and the unglamorous tasks that actually preserve timelines. We confirm permits, credential needs, and staging pads with photos, measurements, and contacts so the driver handshake is more than a blind guess. Dispatch receives scenario scripts for weather, traffic gridlock, or celebrity security tweaks, and we mirror those scripts for the host team. Every loop has a dwell budget, fuel plan, restroom strategy, and spare vehicle logic documented in plain English. Because our on-site captains have direct radio or WhatsApp channels with chauffeurs, we can pulse information before a delay becomes a stall. That muscle memory turns potential chaos into small course corrections riders never notice.\n\nAmenities are curated intentionally instead of sprinkled randomly, with the spotlight on soft sided coolers, spill proof tumblers, labeled hydration packs. We compare rider avatars against cabin layouts to decide where hydration stations, photo props, vow cards, or merch drops should live. Hosts receive a diagram that labels every comfort touch so they know what to hype on the mic, what to protect from overuse, and when to refresh each zone. When a vehicle swap happens, our amenity trunks and digital signage kits move too, which keeps the vibe consistent. We also script how chauffeurs or onboard concierges introduce the upgrades so the spend feels premium rather than gimmicky. Done right, the amenities quietly accelerate boarding, encourage social sharing, and keep the story cohesive from stop to stop.\n\nBudget modeling is transparent because we tie every dollar to a measurable constraint, especially around bulk club runs, bartender staffing, insurance surcharges baked into flat fees. Finance leaders see the decision matrix that compares doing nothing, DIY attempts, or hiring the operator to handle it turnkey. We highlight the costs of failure—injury claims, overtime spirals, missed sponsorship impressions—so approvals feel logical, not emotional. During build-out we log which lines are flexible and which are sacred, making it easier to pivot if the group size or routing changes. Deposits, milestone payments, and gratuity plans are stored in a single tracker to prevent the dreaded text chain of “who still owes what.” With that clarity, stakeholders stay calm even when the scope evolves because they understand the tradeoffs.\n\nExperience design pulls everything together with signature punch cards, playlist cues for water breaks, safe ride share fallback codes so guests feel guided instead of herded. We coach emcees, chauffeurs, and onboard crew on language that is inclusive, celebratory, and sensitive to the group’s culture. Live comms go out through SMS, WhatsApp, and QR-enabled microsites so riders always know where to stand, what is next, and who to text for help. Our media team stages photo or video beats that match the narrative arc, whether that is a reveal moment, a toast, or a chill reset. Post-trip surveys gather candid feedback plus testimonials the client can reuse internally, giving the transportation line item long-tail value. When riders feel seen at every touchpoint, the charter becomes part of the story instead of just a shuttle.\n\nIf you want this level of rigor for your own byob on party buses: rules, coolers, and no-glass tips, tap the Bus2Ride concierge team and we will adapt the playbook to your city. We can collaborate directly with venues, production partners, hotels, or corporate travel managers and share our dashboards so everyone watches the same KPIs. Send a quick brief to info@bus2ride.com or call (888) 535-2566, and we will workshop route ideas, budgets, and backup plans in the first conversation. From there we lock in the exact fleet mix, staffing model, and amenity set that makes your brand, family, or fan base feel unstoppable.",
    "wordCount": 885,
    "thumbnail_url": "blog/BYOB on Party Bus.jpg",
    "published_at": "2025-01-11T12:00:00Z",
    "created_at": "2025-01-11T12:00:00Z",
    "updated_at": "2025-01-11T12:00:00Z",
    "keywords": [
      "BYOB",
      "party bus",
      "safety"
    ],
    "introHook": "Most municipalities allow rider supplied beverages, but only if you choreograph paperwork, containers, and host scripts.",
    "planningFocus": "permit checks, rider waivers, captain assignments for cooler resets",
    "logisticsFocus": "ice swaps at fuel stops, trash rotations, sealed glass drop bins with locks",
    "amenitiesFocus": "soft sided coolers, spill proof tumblers, labeled hydration packs",
    "budgetFocus": "bulk club runs, bartender staffing, insurance surcharges baked into flat fees",
    "experienceFocus": "signature punch cards, playlist cues for water breaks, safe ride share fallback codes"
  },
  {
    "id": "casino-trips-by-coach-comfort-perks-that-matter-most",
    "slug": "casino-trips-by-coach-comfort-perks-that-matter-most",
    "title": "Casino Trips by Coach: Comfort Perks That Matter",
    "excerpt": "Level up gaming runs with reclining coaches, snack service, and tier-based host touchpoints.",
    "content": "It is easy to romanticize casino trips by coach: comfort perks that matter, but High rollers expect the same steakhouse-level hospitality during the transfer that they receive on the casino floor. Bus2Ride treats every transport storyboard as a live operations document where each promise has an owner and a timestamp. We convert the directional keywords you keep repeating—Casino, Trips, Coach, Comfort—into routing guardrails, staffing ratios, and guest communications. That discipline keeps stakeholders aligned even when celebrity handlers, weather alerts, or late sponsor asks enter the chat at the last minute. By defining success through rider outcomes instead of vehicle specs, the rest of the planning stack becomes calmer and measurably more resilient. The goal is a weekend or single-night move that still feels effortless to guests while your logistics brain knows every variable has a backup.\n\nPlanning begins weeks upstream with discovery calls, forms, and scouting drives anchored around player tier manifests, players club coordination, wristband packet stuffing. We map each traveler persona against the run of show so no one is surprised by attire changes, ADA requirements, or last minute VIP arrivals. Our producers draft layered itineraries that explain who greets whom, which curb is primary versus fallback, and what copy needs to be printed for signage. That documentation lets executives, wedding planners, campus staff, or brand teams sign off quickly because they can see the downstream effect of every choice. We also log no-go rules—the songs that must play, the neighborhoods to avoid, the shots the photographer is chasing—so host energy stays protected. When the planning stack reaches that clarity, even complex casino, coach bus, amenities programs feel approachable.\n\nLogistics rehearsal focuses on rest stop rotations, cage cash escort timing, luggage bell desk runs and the unglamorous tasks that actually preserve timelines. We confirm permits, credential needs, and staging pads with photos, measurements, and contacts so the driver handshake is more than a blind guess. Dispatch receives scenario scripts for weather, traffic gridlock, or celebrity security tweaks, and we mirror those scripts for the host team. Every loop has a dwell budget, fuel plan, restroom strategy, and spare vehicle logic documented in plain English. Because our on-site captains have direct radio or WhatsApp channels with chauffeurs, we can pulse information before a delay becomes a stall. That muscle memory turns potential chaos into small course corrections riders never notice.\n\nAmenities are curated intentionally instead of sprinkled randomly, with the spotlight on recliners, footrests, gaming themed snacks, hot towel service. We compare rider avatars against cabin layouts to decide where hydration stations, photo props, vow cards, or merch drops should live. Hosts receive a diagram that labels every comfort touch so they know what to hype on the mic, what to protect from overuse, and when to refresh each zone. When a vehicle swap happens, our amenity trunks and digital signage kits move too, which keeps the vibe consistent. We also script how chauffeurs or onboard concierges introduce the upgrades so the spend feels premium rather than gimmicky. Done right, the amenities quietly accelerate boarding, encourage social sharing, and keep the story cohesive from stop to stop.\n\nBudget modeling is transparent because we tie every dollar to a measurable constraint, especially around rebate negotiations, slot credit bundles, host comp tracking. Finance leaders see the decision matrix that compares doing nothing, DIY attempts, or hiring the operator to handle it turnkey. We highlight the costs of failure—injury claims, overtime spirals, missed sponsorship impressions—so approvals feel logical, not emotional. During build-out we log which lines are flexible and which are sacred, making it easier to pivot if the group size or routing changes. Deposits, milestone payments, and gratuity plans are stored in a single tracker to prevent the dreaded text chain of “who still owes what.” With that clarity, stakeholders stay calm even when the scope evolves because they understand the tradeoffs.\n\nExperience design pulls everything together with table reservation confirmations, live leaderboard texts, end of night recaps for VIP liaisons so guests feel guided instead of herded. We coach emcees, chauffeurs, and onboard crew on language that is inclusive, celebratory, and sensitive to the group’s culture. Live comms go out through SMS, WhatsApp, and QR-enabled microsites so riders always know where to stand, what is next, and who to text for help. Our media team stages photo or video beats that match the narrative arc, whether that is a reveal moment, a toast, or a chill reset. Post-trip surveys gather candid feedback plus testimonials the client can reuse internally, giving the transportation line item long-tail value. When riders feel seen at every touchpoint, the charter becomes part of the story instead of just a shuttle.\n\nIf you want this level of rigor for your own casino trips by coach: comfort perks that matter, tap the Bus2Ride concierge team and we will adapt the playbook to your city. We can collaborate directly with venues, production partners, hotels, or corporate travel managers and share our dashboards so everyone watches the same KPIs. Send a quick brief to info@bus2ride.com or call (888) 535-2566, and we will workshop route ideas, budgets, and backup plans in the first conversation. From there we lock in the exact fleet mix, staffing model, and amenity set that makes your brand, family, or fan base feel unstoppable.",
    "wordCount": 878,
    "thumbnail_url": "blog/Casino Trips.jpg",
    "published_at": "2025-01-12T12:00:00Z",
    "created_at": "2025-01-12T12:00:00Z",
    "updated_at": "2025-01-12T12:00:00Z",
    "keywords": [
      "casino",
      "coach bus",
      "amenities"
    ],
    "introHook": "High rollers expect the same steakhouse-level hospitality during the transfer that they receive on the casino floor.",
    "planningFocus": "player tier manifests, players club coordination, wristband packet stuffing",
    "logisticsFocus": "rest stop rotations, cage cash escort timing, luggage bell desk runs",
    "amenitiesFocus": "recliners, footrests, gaming themed snacks, hot towel service",
    "budgetFocus": "rebate negotiations, slot credit bundles, host comp tracking",
    "experienceFocus": "table reservation confirmations, live leaderboard texts, end of night recaps for VIP liaisons"
  },
  {
    "id": "city-traffic-101-building-realistic-timelines",
    "slug": "city-traffic-101-building-realistic-timelines",
    "title": "City Traffic 101: Building Realistic Timelines",
    "excerpt": "Translate DOT data, event calendars, and construction feeds into buffers that keep buses punctual.",
    "content": "It is easy to romanticize city traffic 101: building realistic timelines, but Urban transfers fail when planners trust speed limits instead of lived congestion math. Bus2Ride treats every transport storyboard as a live operations document where each promise has an owner and a timestamp. We convert the directional keywords you keep repeating—City, Traffic, 101, Building—into routing guardrails, staffing ratios, and guest communications. That discipline keeps stakeholders aligned even when celebrity handlers, weather alerts, or late sponsor asks enter the chat at the last minute. By defining success through rider outcomes instead of vehicle specs, the rest of the planning stack becomes calmer and measurably more resilient. The goal is a weekend or single-night move that still feels effortless to guests while your logistics brain knows every variable has a backup.\n\nPlanning begins weeks upstream with discovery calls, forms, and scouting drives anchored around scouting drives, beta rideshare timing pulls, color coded buffer grids. We map each traveler persona against the run of show so no one is surprised by attire changes, ADA requirements, or last minute VIP arrivals. Our producers draft layered itineraries that explain who greets whom, which curb is primary versus fallback, and what copy needs to be printed for signage. That documentation lets executives, wedding planners, campus staff, or brand teams sign off quickly because they can see the downstream effect of every choice. We also log no-go rules—the songs that must play, the neighborhoods to avoid, the shots the photographer is chasing—so host energy stays protected. When the planning stack reaches that clarity, even complex traffic, timelines, planning programs feel approachable.\n\nLogistics rehearsal focuses on traffic officer coordination, detour binders, parallel routing for VIPs and the unglamorous tasks that actually preserve timelines. We confirm permits, credential needs, and staging pads with photos, measurements, and contacts so the driver handshake is more than a blind guess. Dispatch receives scenario scripts for weather, traffic gridlock, or celebrity security tweaks, and we mirror those scripts for the host team. Every loop has a dwell budget, fuel plan, restroom strategy, and spare vehicle logic documented in plain English. Because our on-site captains have direct radio or WhatsApp channels with chauffeurs, we can pulse information before a delay becomes a stall. That muscle memory turns potential chaos into small course corrections riders never notice.\n\nAmenities are curated intentionally instead of sprinkled randomly, with the spotlight on cabin comms screens showing ETA honesty, snack caches for unexpected holds. We compare rider avatars against cabin layouts to decide where hydration stations, photo props, vow cards, or merch drops should live. Hosts receive a diagram that labels every comfort touch so they know what to hype on the mic, what to protect from overuse, and when to refresh each zone. When a vehicle swap happens, our amenity trunks and digital signage kits move too, which keeps the vibe consistent. We also script how chauffeurs or onboard concierges introduce the upgrades so the spend feels premium rather than gimmicky. Done right, the amenities quietly accelerate boarding, encourage social sharing, and keep the story cohesive from stop to stop.\n\nBudget modeling is transparent because we tie every dollar to a measurable constraint, especially around overtime forecasts, standby vehicle retainers, toll transponder preloads. Finance leaders see the decision matrix that compares doing nothing, DIY attempts, or hiring the operator to handle it turnkey. We highlight the costs of failure—injury claims, overtime spirals, missed sponsorship impressions—so approvals feel logical, not emotional. During build-out we log which lines are flexible and which are sacred, making it easier to pivot if the group size or routing changes. Deposits, milestone payments, and gratuity plans are stored in a single tracker to prevent the dreaded text chain of “who still owes what.” With that clarity, stakeholders stay calm even when the scope evolves because they understand the tradeoffs.\n\nExperience design pulls everything together with proactive comms to guests with map snippets, apology swag if delays spike, after action traffic reports so guests feel guided instead of herded. We coach emcees, chauffeurs, and onboard crew on language that is inclusive, celebratory, and sensitive to the group’s culture. Live comms go out through SMS, WhatsApp, and QR-enabled microsites so riders always know where to stand, what is next, and who to text for help. Our media team stages photo or video beats that match the narrative arc, whether that is a reveal moment, a toast, or a chill reset. Post-trip surveys gather candid feedback plus testimonials the client can reuse internally, giving the transportation line item long-tail value. When riders feel seen at every touchpoint, the charter becomes part of the story instead of just a shuttle.\n\nIf you want this level of rigor for your own city traffic 101: building realistic timelines, tap the Bus2Ride concierge team and we will adapt the playbook to your city. We can collaborate directly with venues, production partners, hotels, or corporate travel managers and share our dashboards so everyone watches the same KPIs. Send a quick brief to info@bus2ride.com or call (888) 535-2566, and we will workshop route ideas, budgets, and backup plans in the first conversation. From there we lock in the exact fleet mix, staffing model, and amenity set that makes your brand, family, or fan base feel unstoppable.",
    "wordCount": 874,
    "thumbnail_url": "blog/City Traffic.jpg",
    "published_at": "2025-01-13T12:00:00Z",
    "created_at": "2025-01-13T12:00:00Z",
    "updated_at": "2025-01-13T12:00:00Z",
    "keywords": [
      "traffic",
      "timelines",
      "planning"
    ],
    "introHook": "Urban transfers fail when planners trust speed limits instead of lived congestion math.",
    "planningFocus": "scouting drives, beta rideshare timing pulls, color coded buffer grids",
    "logisticsFocus": "traffic officer coordination, detour binders, parallel routing for VIPs",
    "amenitiesFocus": "cabin comms screens showing ETA honesty, snack caches for unexpected holds",
    "budgetFocus": "overtime forecasts, standby vehicle retainers, toll transponder preloads",
    "experienceFocus": "proactive comms to guests with map snippets, apology swag if delays spike, after action traffic reports"
  },
  {
    "id": "cold-weather-rides-winter-tips-for-limos-buses",
    "slug": "cold-weather-rides-winter-tips-for-limos-buses",
    "title": "Cold-Weather Rides: Winter Tips for Limos & Buses",
    "excerpt": "Winterize itineraries with tire plans, coat storage, and coco stations so riders stay warm between venues.",
    "content": "It is easy to romanticize cold-weather rides: winter tips for limos & buses, but Snow, black ice, and frozen door seals make winter charters unforgiving unless you choreograph every warm touchpoint. Bus2Ride treats every transport storyboard as a live operations document where each promise has an owner and a timestamp. We convert the directional keywords you keep repeating—Cold, Weather, Rides, Winter—into routing guardrails, staffing ratios, and guest communications. That discipline keeps stakeholders aligned even when celebrity handlers, weather alerts, or late sponsor asks enter the chat at the last minute. By defining success through rider outcomes instead of vehicle specs, the rest of the planning stack becomes calmer and measurably more resilient. The goal is a weekend or single-night move that still feels effortless to guests while your logistics brain knows every variable has a backup.\n\nPlanning begins weeks upstream with discovery calls, forms, and scouting drives anchored around storm monitoring cadences, alternate venue holds, winter SOP briefings. We map each traveler persona against the run of show so no one is surprised by attire changes, ADA requirements, or last minute VIP arrivals. Our producers draft layered itineraries that explain who greets whom, which curb is primary versus fallback, and what copy needs to be printed for signage. That documentation lets executives, wedding planners, campus staff, or brand teams sign off quickly because they can see the downstream effect of every choice. We also log no-go rules—the songs that must play, the neighborhoods to avoid, the shots the photographer is chasing—so host energy stays protected. When the planning stack reaches that clarity, even complex winter, safety, fleet programs feel approachable.\n\nLogistics rehearsal focuses on heated staging pads, salt sweeps, pre trip block heaters with checklists and the unglamorous tasks that actually preserve timelines. We confirm permits, credential needs, and staging pads with photos, measurements, and contacts so the driver handshake is more than a blind guess. Dispatch receives scenario scripts for weather, traffic gridlock, or celebrity security tweaks, and we mirror those scripts for the host team. Every loop has a dwell budget, fuel plan, restroom strategy, and spare vehicle logic documented in plain English. Because our on-site captains have direct radio or WhatsApp channels with chauffeurs, we can pulse information before a delay becomes a stall. That muscle memory turns potential chaos into small course corrections riders never notice.\n\nAmenities are curated intentionally instead of sprinkled randomly, with the spotlight on blanket lockers, coat valets, hot beverage urns with secure mounts. We compare rider avatars against cabin layouts to decide where hydration stations, photo props, vow cards, or merch drops should live. Hosts receive a diagram that labels every comfort touch so they know what to hype on the mic, what to protect from overuse, and when to refresh each zone. When a vehicle swap happens, our amenity trunks and digital signage kits move too, which keeps the vibe consistent. We also script how chauffeurs or onboard concierges introduce the upgrades so the spend feels premium rather than gimmicky. Done right, the amenities quietly accelerate boarding, encourage social sharing, and keep the story cohesive from stop to stop.\n\nBudget modeling is transparent because we tie every dollar to a measurable constraint, especially around snow labor retainers, de-icing supplies, weather insurance riders. Finance leaders see the decision matrix that compares doing nothing, DIY attempts, or hiring the operator to handle it turnkey. We highlight the costs of failure—injury claims, overtime spirals, missed sponsorship impressions—so approvals feel logical, not emotional. During build-out we log which lines are flexible and which are sacred, making it easier to pivot if the group size or routing changes. Deposits, milestone payments, and gratuity plans are stored in a single tracker to prevent the dreaded text chain of “who still owes what.” With that clarity, stakeholders stay calm even when the scope evolves because they understand the tradeoffs.\n\nExperience design pulls everything together with text trees with storm updates, cocoa welcome shots, gratitude notes to crews who braved the cold so guests feel guided instead of herded. We coach emcees, chauffeurs, and onboard crew on language that is inclusive, celebratory, and sensitive to the group’s culture. Live comms go out through SMS, WhatsApp, and QR-enabled microsites so riders always know where to stand, what is next, and who to text for help. Our media team stages photo or video beats that match the narrative arc, whether that is a reveal moment, a toast, or a chill reset. Post-trip surveys gather candid feedback plus testimonials the client can reuse internally, giving the transportation line item long-tail value. When riders feel seen at every touchpoint, the charter becomes part of the story instead of just a shuttle.\n\nIf you want this level of rigor for your own cold-weather rides: winter tips for limos & buses, tap the Bus2Ride concierge team and we will adapt the playbook to your city. We can collaborate directly with venues, production partners, hotels, or corporate travel managers and share our dashboards so everyone watches the same KPIs. Send a quick brief to info@bus2ride.com or call (888) 535-2566, and we will workshop route ideas, budgets, and backup plans in the first conversation. From there we lock in the exact fleet mix, staffing model, and amenity set that makes your brand, family, or fan base feel unstoppable.",
    "wordCount": 882,
    "thumbnail_url": "blog/Cold Weather.jpg",
    "published_at": "2025-01-14T12:00:00Z",
    "created_at": "2025-01-14T12:00:00Z",
    "updated_at": "2025-01-14T12:00:00Z",
    "keywords": [
      "winter",
      "safety",
      "fleet"
    ],
    "introHook": "Snow, black ice, and frozen door seals make winter charters unforgiving unless you choreograph every warm touchpoint.",
    "planningFocus": "storm monitoring cadences, alternate venue holds, winter SOP briefings",
    "logisticsFocus": "heated staging pads, salt sweeps, pre trip block heaters with checklists",
    "amenitiesFocus": "blanket lockers, coat valets, hot beverage urns with secure mounts",
    "budgetFocus": "snow labor retainers, de-icing supplies, weather insurance riders",
    "experienceFocus": "text trees with storm updates, cocoa welcome shots, gratitude notes to crews who braved the cold"
  },
  {
    "id": "concert-nights-by-bus-tailgating-parking-drop-zones",
    "slug": "concert-nights-by-bus-tailgating-parking-drop-zones",
    "title": "Concert Nights by Bus: Tailgating, Parking, Drop Zones",
    "excerpt": "Beat arena chaos with tailgate staging, merch hauls, and escorts who know every loading dock.",
    "content": "It is easy to romanticize concert nights by bus: tailgating, parking, drop zones, but Festivals stack multiple load-ins, so your routes need credentialed marshals and backup lots ready to go. Bus2Ride treats every transport storyboard as a live operations document where each promise has an owner and a timestamp. We convert the directional keywords you keep repeating—Concert, Nights, Bus, Tailgating—into routing guardrails, staffing ratios, and guest communications. That discipline keeps stakeholders aligned even when celebrity handlers, weather alerts, or late sponsor asks enter the chat at the last minute. By defining success through rider outcomes instead of vehicle specs, the rest of the planning stack becomes calmer and measurably more resilient. The goal is a weekend or single-night move that still feels effortless to guests while your logistics brain knows every variable has a backup.\n\nPlanning begins weeks upstream with discovery calls, forms, and scouting drives anchored around ticket groupings, wristband scanning at check in, tailgate menu boards. We map each traveler persona against the run of show so no one is surprised by attire changes, ADA requirements, or last minute VIP arrivals. Our producers draft layered itineraries that explain who greets whom, which curb is primary versus fallback, and what copy needs to be printed for signage. That documentation lets executives, wedding planners, campus staff, or brand teams sign off quickly because they can see the downstream effect of every choice. We also log no-go rules—the songs that must play, the neighborhoods to avoid, the shots the photographer is chasing—so host energy stays protected. When the planning stack reaches that clarity, even complex concert, tailgate, parking programs feel approachable.\n\nLogistics rehearsal focuses on police escorts, holding lot rotations, megaphone scripts for reboarding and the unglamorous tasks that actually preserve timelines. We confirm permits, credential needs, and staging pads with photos, measurements, and contacts so the driver handshake is more than a blind guess. Dispatch receives scenario scripts for weather, traffic gridlock, or celebrity security tweaks, and we mirror those scripts for the host team. Every loop has a dwell budget, fuel plan, restroom strategy, and spare vehicle logic documented in plain English. Because our on-site captains have direct radio or WhatsApp channels with chauffeurs, we can pulse information before a delay becomes a stall. That muscle memory turns potential chaos into small course corrections riders never notice.\n\nAmenities are curated intentionally instead of sprinkled randomly, with the spotlight on portable chargers, branded ponchos, LED wristbands tied to the headliner finale. We compare rider avatars against cabin layouts to decide where hydration stations, photo props, vow cards, or merch drops should live. Hosts receive a diagram that labels every comfort touch so they know what to hype on the mic, what to protect from overuse, and when to refresh each zone. When a vehicle swap happens, our amenity trunks and digital signage kits move too, which keeps the vibe consistent. We also script how chauffeurs or onboard concierges introduce the upgrades so the spend feels premium rather than gimmicky. Done right, the amenities quietly accelerate boarding, encourage social sharing, and keep the story cohesive from stop to stop.\n\nBudget modeling is transparent because we tie every dollar to a measurable constraint, especially around premium lot fees, security overtime, damage deposits for parking passes. Finance leaders see the decision matrix that compares doing nothing, DIY attempts, or hiring the operator to handle it turnkey. We highlight the costs of failure—injury claims, overtime spirals, missed sponsorship impressions—so approvals feel logical, not emotional. During build-out we log which lines are flexible and which are sacred, making it easier to pivot if the group size or routing changes. Deposits, milestone payments, and gratuity plans are stored in a single tracker to prevent the dreaded text chain of “who still owes what.” With that clarity, stakeholders stay calm even when the scope evolves because they understand the tradeoffs.\n\nExperience design pulls everything together with set list themed snacks, fan photo ops, next morning merch tracking links so guests feel guided instead of herded. We coach emcees, chauffeurs, and onboard crew on language that is inclusive, celebratory, and sensitive to the group’s culture. Live comms go out through SMS, WhatsApp, and QR-enabled microsites so riders always know where to stand, what is next, and who to text for help. Our media team stages photo or video beats that match the narrative arc, whether that is a reveal moment, a toast, or a chill reset. Post-trip surveys gather candid feedback plus testimonials the client can reuse internally, giving the transportation line item long-tail value. When riders feel seen at every touchpoint, the charter becomes part of the story instead of just a shuttle.\n\nIf you want this level of rigor for your own concert nights by bus: tailgating, parking, drop zones, tap the Bus2Ride concierge team and we will adapt the playbook to your city. We can collaborate directly with venues, production partners, hotels, or corporate travel managers and share our dashboards so everyone watches the same KPIs. Send a quick brief to info@bus2ride.com or call (888) 535-2566, and we will workshop route ideas, budgets, and backup plans in the first conversation. From there we lock in the exact fleet mix, staffing model, and amenity set that makes your brand, family, or fan base feel unstoppable.",
    "wordCount": 879,
    "thumbnail_url": "blog/Concerts.jpg",
    "published_at": "2025-01-15T12:00:00Z",
    "created_at": "2025-01-15T12:00:00Z",
    "updated_at": "2025-01-15T12:00:00Z",
    "keywords": [
      "concert",
      "tailgate",
      "parking"
    ],
    "introHook": "Festivals stack multiple load-ins, so your routes need credentialed marshals and backup lots ready to go.",
    "planningFocus": "ticket groupings, wristband scanning at check in, tailgate menu boards",
    "logisticsFocus": "police escorts, holding lot rotations, megaphone scripts for reboarding",
    "amenitiesFocus": "portable chargers, branded ponchos, LED wristbands tied to the headliner finale",
    "budgetFocus": "premium lot fees, security overtime, damage deposits for parking passes",
    "experienceFocus": "set list themed snacks, fan photo ops, next morning merch tracking links"
  },
  {
    "id": "corporate-shuttles-build-a-smooth-event-transportation-plan",
    "slug": "corporate-shuttles-build-a-smooth-event-transportation-plan",
    "title": "Corporate Shuttles: Build a Smooth Event Transportation Plan",
    "excerpt": "Transform chaotic conference bus loops into branded, data-backed shuttle systems executives trust.",
    "content": "It is easy to romanticize corporate shuttles: build a smooth event transportation plan, but Executive teams judge your event long before the keynote, and shuttle dwell is the first KPI they feel. Bus2Ride treats every transport storyboard as a live operations document where each promise has an owner and a timestamp. We convert the directional keywords you keep repeating—Corporate, Shuttles, Build, Smooth—into routing guardrails, staffing ratios, and guest communications. That discipline keeps stakeholders aligned even when celebrity handlers, weather alerts, or late sponsor asks enter the chat at the last minute. By defining success through rider outcomes instead of vehicle specs, the rest of the planning stack becomes calmer and measurably more resilient. The goal is a weekend or single-night move that still feels effortless to guests while your logistics brain knows every variable has a backup.\n\nPlanning begins weeks upstream with discovery calls, forms, and scouting drives anchored around hotel stack matrices, manifest APIs, bilingual signage scripting. We map each traveler persona against the run of show so no one is surprised by attire changes, ADA requirements, or last minute VIP arrivals. Our producers draft layered itineraries that explain who greets whom, which curb is primary versus fallback, and what copy needs to be printed for signage. That documentation lets executives, wedding planners, campus staff, or brand teams sign off quickly because they can see the downstream effect of every choice. We also log no-go rules—the songs that must play, the neighborhoods to avoid, the shots the photographer is chasing—so host energy stays protected. When the planning stack reaches that clarity, even complex corporate, shuttle, operations programs feel approachable.\n\nLogistics rehearsal focuses on RFID rider counts, dispatcher pods, traffic control charters with city partners and the unglamorous tasks that actually preserve timelines. We confirm permits, credential needs, and staging pads with photos, measurements, and contacts so the driver handshake is more than a blind guess. Dispatch receives scenario scripts for weather, traffic gridlock, or celebrity security tweaks, and we mirror those scripts for the host team. Every loop has a dwell budget, fuel plan, restroom strategy, and spare vehicle logic documented in plain English. Because our on-site captains have direct radio or WhatsApp channels with chauffeurs, we can pulse information before a delay becomes a stall. That muscle memory turns potential chaos into small course corrections riders never notice.\n\nAmenities are curated intentionally instead of sprinkled randomly, with the spotlight on seat drop collateral, hydration pallets, ambient playlists that match the brand. We compare rider avatars against cabin layouts to decide where hydration stations, photo props, vow cards, or merch drops should live. Hosts receive a diagram that labels every comfort touch so they know what to hype on the mic, what to protect from overuse, and when to refresh each zone. When a vehicle swap happens, our amenity trunks and digital signage kits move too, which keeps the vibe consistent. We also script how chauffeurs or onboard concierges introduce the upgrades so the spend feels premium rather than gimmicky. Done right, the amenities quietly accelerate boarding, encourage social sharing, and keep the story cohesive from stop to stop.\n\nBudget modeling is transparent because we tie every dollar to a measurable constraint, especially around per-route cost models, incremental bus triggers, sponsor underwriting pitches. Finance leaders see the decision matrix that compares doing nothing, DIY attempts, or hiring the operator to handle it turnkey. We highlight the costs of failure—injury claims, overtime spirals, missed sponsorship impressions—so approvals feel logical, not emotional. During build-out we log which lines are flexible and which are sacred, making it easier to pivot if the group size or routing changes. Deposits, milestone payments, and gratuity plans are stored in a single tracker to prevent the dreaded text chain of “who still owes what.” With that clarity, stakeholders stay calm even when the scope evolves because they understand the tradeoffs.\n\nExperience design pulls everything together with command center dashboards, real time text alerts, post show ops decks that prove success so guests feel guided instead of herded. We coach emcees, chauffeurs, and onboard crew on language that is inclusive, celebratory, and sensitive to the group’s culture. Live comms go out through SMS, WhatsApp, and QR-enabled microsites so riders always know where to stand, what is next, and who to text for help. Our media team stages photo or video beats that match the narrative arc, whether that is a reveal moment, a toast, or a chill reset. Post-trip surveys gather candid feedback plus testimonials the client can reuse internally, giving the transportation line item long-tail value. When riders feel seen at every touchpoint, the charter becomes part of the story instead of just a shuttle.\n\nIf you want this level of rigor for your own corporate shuttles: build a smooth event transportation plan, tap the Bus2Ride concierge team and we will adapt the playbook to your city. We can collaborate directly with venues, production partners, hotels, or corporate travel managers and share our dashboards so everyone watches the same KPIs. Send a quick brief to info@bus2ride.com or call (888) 535-2566, and we will workshop route ideas, budgets, and backup plans in the first conversation. From there we lock in the exact fleet mix, staffing model, and amenity set that makes your brand, family, or fan base feel unstoppable.",
    "wordCount": 882,
    "thumbnail_url": "blog/Corporate Transfers.jpg",
    "published_at": "2025-01-16T12:00:00Z",
    "created_at": "2025-01-16T12:00:00Z",
    "updated_at": "2025-01-16T12:00:00Z",
    "keywords": [
      "corporate",
      "shuttle",
      "operations"
    ],
    "introHook": "Executive teams judge your event long before the keynote, and shuttle dwell is the first KPI they feel.",
    "planningFocus": "hotel stack matrices, manifest APIs, bilingual signage scripting",
    "logisticsFocus": "RFID rider counts, dispatcher pods, traffic control charters with city partners",
    "amenitiesFocus": "seat drop collateral, hydration pallets, ambient playlists that match the brand",
    "budgetFocus": "per-route cost models, incremental bus triggers, sponsor underwriting pitches",
    "experienceFocus": "command center dashboards, real time text alerts, post show ops decks that prove success"
  },
  {
    "id": "game-day-charters-tailgate-setups-stadium-logistics",
    "slug": "game-day-charters-tailgate-setups-stadium-logistics",
    "title": "Game Day Charters: Tailgate Setups & Stadium Logistics",
    "excerpt": "Deliver stadium runs with pro-tailgate staging, fan engagement captains, and exit plans that beat traffic.",
    "content": "It is easy to romanticize game day charters: tailgate setups & stadium logistics, but College and pro venues operate like small cities, so treat them with military precision. Bus2Ride treats every transport storyboard as a live operations document where each promise has an owner and a timestamp. We convert the directional keywords you keep repeating—Game, Day, Charters, Tailgate—into routing guardrails, staffing ratios, and guest communications. That discipline keeps stakeholders aligned even when celebrity handlers, weather alerts, or late sponsor asks enter the chat at the last minute. By defining success through rider outcomes instead of vehicle specs, the rest of the planning stack becomes calmer and measurably more resilient. The goal is a weekend or single-night move that still feels effortless to guests while your logistics brain knows every variable has a backup.\n\nPlanning begins weeks upstream with discovery calls, forms, and scouting drives anchored around ticket pods, alumni host rotations, mascot cameos timed with arrivals. We map each traveler persona against the run of show so no one is surprised by attire changes, ADA requirements, or last minute VIP arrivals. Our producers draft layered itineraries that explain who greets whom, which curb is primary versus fallback, and what copy needs to be printed for signage. That documentation lets executives, wedding planners, campus staff, or brand teams sign off quickly because they can see the downstream effect of every choice. We also log no-go rules—the songs that must play, the neighborhoods to avoid, the shots the photographer is chasing—so host energy stays protected. When the planning stack reaches that clarity, even complex game day, tailgate, charter programs feel approachable.\n\nLogistics rehearsal focuses on lot credential packets, grill drop permits, post game escape lanes and the unglamorous tasks that actually preserve timelines. We confirm permits, credential needs, and staging pads with photos, measurements, and contacts so the driver handshake is more than a blind guess. Dispatch receives scenario scripts for weather, traffic gridlock, or celebrity security tweaks, and we mirror those scripts for the host team. Every loop has a dwell budget, fuel plan, restroom strategy, and spare vehicle logic documented in plain English. Because our on-site captains have direct radio or WhatsApp channels with chauffeurs, we can pulse information before a delay becomes a stall. That muscle memory turns potential chaos into small course corrections riders never notice.\n\nAmenities are curated intentionally instead of sprinkled randomly, with the spotlight on team color lighting, coolers sorted by drink type, rally towel walls. We compare rider avatars against cabin layouts to decide where hydration stations, photo props, vow cards, or merch drops should live. Hosts receive a diagram that labels every comfort touch so they know what to hype on the mic, what to protect from overuse, and when to refresh each zone. When a vehicle swap happens, our amenity trunks and digital signage kits move too, which keeps the vibe consistent. We also script how chauffeurs or onboard concierges introduce the upgrades so the spend feels premium rather than gimmicky. Done right, the amenities quietly accelerate boarding, encourage social sharing, and keep the story cohesive from stop to stop.\n\nBudget modeling is transparent because we tie every dollar to a measurable constraint, especially around sponsor tent offsets, shared security costs, cleanup crews baked into rates. Finance leaders see the decision matrix that compares doing nothing, DIY attempts, or hiring the operator to handle it turnkey. We highlight the costs of failure—injury claims, overtime spirals, missed sponsorship impressions—so approvals feel logical, not emotional. During build-out we log which lines are flexible and which are sacred, making it easier to pivot if the group size or routing changes. Deposits, milestone payments, and gratuity plans are stored in a single tracker to prevent the dreaded text chain of “who still owes what.” With that clarity, stakeholders stay calm even when the scope evolves because they understand the tradeoffs.\n\nExperience design pulls everything together with fan chant choreography, live stat push notifications, hero reel recaps for donors so guests feel guided instead of herded. We coach emcees, chauffeurs, and onboard crew on language that is inclusive, celebratory, and sensitive to the group’s culture. Live comms go out through SMS, WhatsApp, and QR-enabled microsites so riders always know where to stand, what is next, and who to text for help. Our media team stages photo or video beats that match the narrative arc, whether that is a reveal moment, a toast, or a chill reset. Post-trip surveys gather candid feedback plus testimonials the client can reuse internally, giving the transportation line item long-tail value. When riders feel seen at every touchpoint, the charter becomes part of the story instead of just a shuttle.\n\nIf you want this level of rigor for your own game day charters: tailgate setups & stadium logistics, tap the Bus2Ride concierge team and we will adapt the playbook to your city. We can collaborate directly with venues, production partners, hotels, or corporate travel managers and share our dashboards so everyone watches the same KPIs. Send a quick brief to info@bus2ride.com or call (888) 535-2566, and we will workshop route ideas, budgets, and backup plans in the first conversation. From there we lock in the exact fleet mix, staffing model, and amenity set that makes your brand, family, or fan base feel unstoppable.",
    "wordCount": 880,
    "thumbnail_url": "blog/Game Day Charters.jpg",
    "published_at": "2025-01-17T12:00:00Z",
    "created_at": "2025-01-17T12:00:00Z",
    "updated_at": "2025-01-17T12:00:00Z",
    "keywords": [
      "game day",
      "tailgate",
      "charter"
    ],
    "introHook": "College and pro venues operate like small cities, so treat them with military precision.",
    "planningFocus": "ticket pods, alumni host rotations, mascot cameos timed with arrivals",
    "logisticsFocus": "lot credential packets, grill drop permits, post game escape lanes",
    "amenitiesFocus": "team color lighting, coolers sorted by drink type, rally towel walls",
    "budgetFocus": "sponsor tent offsets, shared security costs, cleanup crews baked into rates",
    "experienceFocus": "fan chant choreography, live stat push notifications, hero reel recaps for donors"
  },
  {
    "id": "homecoming-school-dances-group-transportation-tips",
    "slug": "homecoming-school-dances-group-transportation-tips",
    "title": "Homecoming & School Dances: Group Transportation Tips",
    "excerpt": "Keep teens safe and chaperones calm with clear rules, verified vendors, and Instagram-ready interiors.",
    "content": "It is easy to romanticize homecoming & school dances: group transportation tips, but Parents want receipts that every adult is background checked and every mile is chaperoned. Bus2Ride treats every transport storyboard as a live operations document where each promise has an owner and a timestamp. We convert the directional keywords you keep repeating—Homecoming, School, Dances, Group—into routing guardrails, staffing ratios, and guest communications. That discipline keeps stakeholders aligned even when celebrity handlers, weather alerts, or late sponsor asks enter the chat at the last minute. By defining success through rider outcomes instead of vehicle specs, the rest of the planning stack becomes calmer and measurably more resilient. The goal is a weekend or single-night move that still feels effortless to guests while your logistics brain knows every variable has a backup.\n\nPlanning begins weeks upstream with discovery calls, forms, and scouting drives anchored around permission slips, parent comms portals, chaperone seating charts. We map each traveler persona against the run of show so no one is surprised by attire changes, ADA requirements, or last minute VIP arrivals. Our producers draft layered itineraries that explain who greets whom, which curb is primary versus fallback, and what copy needs to be printed for signage. That documentation lets executives, wedding planners, campus staff, or brand teams sign off quickly because they can see the downstream effect of every choice. We also log no-go rules—the songs that must play, the neighborhoods to avoid, the shots the photographer is chasing—so host energy stays protected. When the planning stack reaches that clarity, even complex homecoming, school dance, safety programs feel approachable.\n\nLogistics rehearsal focuses on photo stop permits, pre dance snack staging, drop loop rehearsal and the unglamorous tasks that actually preserve timelines. We confirm permits, credential needs, and staging pads with photos, measurements, and contacts so the driver handshake is more than a blind guess. Dispatch receives scenario scripts for weather, traffic gridlock, or celebrity security tweaks, and we mirror those scripts for the host team. Every loop has a dwell budget, fuel plan, restroom strategy, and spare vehicle logic documented in plain English. Because our on-site captains have direct radio or WhatsApp channels with chauffeurs, we can pulse information before a delay becomes a stall. That muscle memory turns potential chaos into small course corrections riders never notice.\n\nAmenities are curated intentionally instead of sprinkled randomly, with the spotlight on glow wristbands, nonalcoholic mocktail bars, selfie lighting rigs. We compare rider avatars against cabin layouts to decide where hydration stations, photo props, vow cards, or merch drops should live. Hosts receive a diagram that labels every comfort touch so they know what to hype on the mic, what to protect from overuse, and when to refresh each zone. When a vehicle swap happens, our amenity trunks and digital signage kits move too, which keeps the vibe consistent. We also script how chauffeurs or onboard concierges introduce the upgrades so the spend feels premium rather than gimmicky. Done right, the amenities quietly accelerate boarding, encourage social sharing, and keep the story cohesive from stop to stop.\n\nBudget modeling is transparent because we tie every dollar to a measurable constraint, especially around per student bundles, booster sponsorships, contingency funds for overtime. Finance leaders see the decision matrix that compares doing nothing, DIY attempts, or hiring the operator to handle it turnkey. We highlight the costs of failure—injury claims, overtime spirals, missed sponsorship impressions—so approvals feel logical, not emotional. During build-out we log which lines are flexible and which are sacred, making it easier to pivot if the group size or routing changes. Deposits, milestone payments, and gratuity plans are stored in a single tracker to prevent the dreaded text chain of “who still owes what.” With that clarity, stakeholders stay calm even when the scope evolves because they understand the tradeoffs.\n\nExperience design pulls everything together with shared photo galleries, gratitude notes to chaperones, next day debrief emails to parents so guests feel guided instead of herded. We coach emcees, chauffeurs, and onboard crew on language that is inclusive, celebratory, and sensitive to the group’s culture. Live comms go out through SMS, WhatsApp, and QR-enabled microsites so riders always know where to stand, what is next, and who to text for help. Our media team stages photo or video beats that match the narrative arc, whether that is a reveal moment, a toast, or a chill reset. Post-trip surveys gather candid feedback plus testimonials the client can reuse internally, giving the transportation line item long-tail value. When riders feel seen at every touchpoint, the charter becomes part of the story instead of just a shuttle.\n\nIf you want this level of rigor for your own homecoming & school dances: group transportation tips, tap the Bus2Ride concierge team and we will adapt the playbook to your city. We can collaborate directly with venues, production partners, hotels, or corporate travel managers and share our dashboards so everyone watches the same KPIs. Send a quick brief to info@bus2ride.com or call (888) 535-2566, and we will workshop route ideas, budgets, and backup plans in the first conversation. From there we lock in the exact fleet mix, staffing model, and amenity set that makes your brand, family, or fan base feel unstoppable.",
    "wordCount": 872,
    "thumbnail_url": "blog/Homecoming.jpg",
    "published_at": "2025-01-18T12:00:00Z",
    "created_at": "2025-01-18T12:00:00Z",
    "updated_at": "2025-01-18T12:00:00Z",
    "keywords": [
      "homecoming",
      "school dance",
      "safety"
    ],
    "introHook": "Parents want receipts that every adult is background checked and every mile is chaperoned.",
    "planningFocus": "permission slips, parent comms portals, chaperone seating charts",
    "logisticsFocus": "photo stop permits, pre dance snack staging, drop loop rehearsal",
    "amenitiesFocus": "glow wristbands, nonalcoholic mocktail bars, selfie lighting rigs",
    "budgetFocus": "per student bundles, booster sponsorships, contingency funds for overtime",
    "experienceFocus": "shared photo galleries, gratitude notes to chaperones, next day debrief emails to parents"
  },
  {
    "id": "how-to-choose-a-local-vendor-reviews-insurance-fleet-age",
    "slug": "how-to-choose-a-local-vendor-reviews-insurance-fleet-age",
    "title": "How to Choose a Local Vendor: Reviews, Insurance, Fleet Age",
    "excerpt": "Build a procurement scorecard that digs deeper than Google stars to verify safety, coverage, and bench strength.",
    "content": "It is easy to romanticize how to choose a local vendor: reviews, insurance, fleet age, but A pretty deck means nothing if the DOT snapshot shows red flags, so investigate before you book. Bus2Ride treats every transport storyboard as a live operations document where each promise has an owner and a timestamp. We convert the directional keywords you keep repeating—Choose, Local, Vendor, Reviews—into routing guardrails, staffing ratios, and guest communications. That discipline keeps stakeholders aligned even when celebrity handlers, weather alerts, or late sponsor asks enter the chat at the last minute. By defining success through rider outcomes instead of vehicle specs, the rest of the planning stack becomes calmer and measurably more resilient. The goal is a weekend or single-night move that still feels effortless to guests while your logistics brain knows every variable has a backup.\n\nPlanning begins weeks upstream with discovery calls, forms, and scouting drives anchored around RFP templates, reference calls, compliance packet trackers. We map each traveler persona against the run of show so no one is surprised by attire changes, ADA requirements, or last minute VIP arrivals. Our producers draft layered itineraries that explain who greets whom, which curb is primary versus fallback, and what copy needs to be printed for signage. That documentation lets executives, wedding planners, campus staff, or brand teams sign off quickly because they can see the downstream effect of every choice. We also log no-go rules—the songs that must play, the neighborhoods to avoid, the shots the photographer is chasing—so host energy stays protected. When the planning stack reaches that clarity, even complex vendors, procurement, compliance programs feel approachable.\n\nLogistics rehearsal focuses on yard visits, surprise inspections, GPS data review to confirm uptime and the unglamorous tasks that actually preserve timelines. We confirm permits, credential needs, and staging pads with photos, measurements, and contacts so the driver handshake is more than a blind guess. Dispatch receives scenario scripts for weather, traffic gridlock, or celebrity security tweaks, and we mirror those scripts for the host team. Every loop has a dwell budget, fuel plan, restroom strategy, and spare vehicle logic documented in plain English. Because our on-site captains have direct radio or WhatsApp channels with chauffeurs, we can pulse information before a delay becomes a stall. That muscle memory turns potential chaos into small course corrections riders never notice.\n\nAmenities are curated intentionally instead of sprinkled randomly, with the spotlight on fleet age breakdowns, retrofit histories, cabin tech audits. We compare rider avatars against cabin layouts to decide where hydration stations, photo props, vow cards, or merch drops should live. Hosts receive a diagram that labels every comfort touch so they know what to hype on the mic, what to protect from overuse, and when to refresh each zone. When a vehicle swap happens, our amenity trunks and digital signage kits move too, which keeps the vibe consistent. We also script how chauffeurs or onboard concierges introduce the upgrades so the spend feels premium rather than gimmicky. Done right, the amenities quietly accelerate boarding, encourage social sharing, and keep the story cohesive from stop to stop.\n\nBudget modeling is transparent because we tie every dollar to a measurable constraint, especially around multi-year rate locks, fuel escalator clauses, penalty language for no-shows. Finance leaders see the decision matrix that compares doing nothing, DIY attempts, or hiring the operator to handle it turnkey. We highlight the costs of failure—injury claims, overtime spirals, missed sponsorship impressions—so approvals feel logical, not emotional. During build-out we log which lines are flexible and which are sacred, making it easier to pivot if the group size or routing changes. Deposits, milestone payments, and gratuity plans are stored in a single tracker to prevent the dreaded text chain of “who still owes what.” With that clarity, stakeholders stay calm even when the scope evolves because they understand the tradeoffs.\n\nExperience design pulls everything together with escalation ladders, shared dashboards, service credits documented in writing so guests feel guided instead of herded. We coach emcees, chauffeurs, and onboard crew on language that is inclusive, celebratory, and sensitive to the group’s culture. Live comms go out through SMS, WhatsApp, and QR-enabled microsites so riders always know where to stand, what is next, and who to text for help. Our media team stages photo or video beats that match the narrative arc, whether that is a reveal moment, a toast, or a chill reset. Post-trip surveys gather candid feedback plus testimonials the client can reuse internally, giving the transportation line item long-tail value. When riders feel seen at every touchpoint, the charter becomes part of the story instead of just a shuttle.\n\nIf you want this level of rigor for your own how to choose a local vendor: reviews, insurance, fleet age, tap the Bus2Ride concierge team and we will adapt the playbook to your city. We can collaborate directly with venues, production partners, hotels, or corporate travel managers and share our dashboards so everyone watches the same KPIs. Send a quick brief to info@bus2ride.com or call (888) 535-2566, and we will workshop route ideas, budgets, and backup plans in the first conversation. From there we lock in the exact fleet mix, staffing model, and amenity set that makes your brand, family, or fan base feel unstoppable.",
    "wordCount": 876,
    "thumbnail_url": "blog/How Choose Local Vendor.jpg",
    "published_at": "2025-01-19T12:00:00Z",
    "created_at": "2025-01-19T12:00:00Z",
    "updated_at": "2025-01-19T12:00:00Z",
    "keywords": [
      "vendors",
      "procurement",
      "compliance"
    ],
    "introHook": "A pretty deck means nothing if the DOT snapshot shows red flags, so investigate before you book.",
    "planningFocus": "RFP templates, reference calls, compliance packet trackers",
    "logisticsFocus": "yard visits, surprise inspections, GPS data review to confirm uptime",
    "amenitiesFocus": "fleet age breakdowns, retrofit histories, cabin tech audits",
    "budgetFocus": "multi-year rate locks, fuel escalator clauses, penalty language for no-shows",
    "experienceFocus": "escalation ladders, shared dashboards, service credits documented in writing"
  },
  {
    "id": "how-early-should-you-book-lead-time-by-season-vehicle",
    "slug": "how-early-should-you-book-lead-time-by-season-vehicle",
    "title": "How Early Should You Book? Lead Time by Season & Vehicle",
    "excerpt": "Match booking windows to peak seasons so you stop refreshing fleet availability in a panic.",
    "content": "It is easy to romanticize how early should you book? lead time by season & vehicle, but Charter supply swings wildly between graduations, foliage tours, and holiday lights, so lead times must flex. Bus2Ride treats every transport storyboard as a live operations document where each promise has an owner and a timestamp. We convert the directional keywords you keep repeating—Early, Should, You, Book—into routing guardrails, staffing ratios, and guest communications. That discipline keeps stakeholders aligned even when celebrity handlers, weather alerts, or late sponsor asks enter the chat at the last minute. By defining success through rider outcomes instead of vehicle specs, the rest of the planning stack becomes calmer and measurably more resilient. The goal is a weekend or single-night move that still feels effortless to guests while your logistics brain knows every variable has a backup.\n\nPlanning begins weeks upstream with discovery calls, forms, and scouting drives anchored around demand calendars, hold release policies, soft versus firm contracts. We map each traveler persona against the run of show so no one is surprised by attire changes, ADA requirements, or last minute VIP arrivals. Our producers draft layered itineraries that explain who greets whom, which curb is primary versus fallback, and what copy needs to be printed for signage. That documentation lets executives, wedding planners, campus staff, or brand teams sign off quickly because they can see the downstream effect of every choice. We also log no-go rules—the songs that must play, the neighborhoods to avoid, the shots the photographer is chasing—so host energy stays protected. When the planning stack reaches that clarity, even complex booking, timelines, seasonality programs feel approachable.\n\nLogistics rehearsal focuses on option expirations, payment triggers, comms workflow when fleets sell out and the unglamorous tasks that actually preserve timelines. We confirm permits, credential needs, and staging pads with photos, measurements, and contacts so the driver handshake is more than a blind guess. Dispatch receives scenario scripts for weather, traffic gridlock, or celebrity security tweaks, and we mirror those scripts for the host team. Every loop has a dwell budget, fuel plan, restroom strategy, and spare vehicle logic documented in plain English. Because our on-site captains have direct radio or WhatsApp channels with chauffeurs, we can pulse information before a delay becomes a stall. That muscle memory turns potential chaos into small course corrections riders never notice.\n\nAmenities are curated intentionally instead of sprinkled randomly, with the spotlight on vehicle swaps, upgrade ladders, seasonal decor storage. We compare rider avatars against cabin layouts to decide where hydration stations, photo props, vow cards, or merch drops should live. Hosts receive a diagram that labels every comfort touch so they know what to hype on the mic, what to protect from overuse, and when to refresh each zone. When a vehicle swap happens, our amenity trunks and digital signage kits move too, which keeps the vibe consistent. We also script how chauffeurs or onboard concierges introduce the upgrades so the spend feels premium rather than gimmicky. Done right, the amenities quietly accelerate boarding, encourage social sharing, and keep the story cohesive from stop to stop.\n\nBudget modeling is transparent because we tie every dollar to a measurable constraint, especially around early bird savings, surge multipliers, refundable deposits strategy. Finance leaders see the decision matrix that compares doing nothing, DIY attempts, or hiring the operator to handle it turnkey. We highlight the costs of failure—injury claims, overtime spirals, missed sponsorship impressions—so approvals feel logical, not emotional. During build-out we log which lines are flexible and which are sacred, making it easier to pivot if the group size or routing changes. Deposits, milestone payments, and gratuity plans are stored in a single tracker to prevent the dreaded text chain of “who still owes what.” With that clarity, stakeholders stay calm even when the scope evolves because they understand the tradeoffs.\n\nExperience design pulls everything together with transparent updates to hosts, alternative routing menus, white glove rebooking support so guests feel guided instead of herded. We coach emcees, chauffeurs, and onboard crew on language that is inclusive, celebratory, and sensitive to the group’s culture. Live comms go out through SMS, WhatsApp, and QR-enabled microsites so riders always know where to stand, what is next, and who to text for help. Our media team stages photo or video beats that match the narrative arc, whether that is a reveal moment, a toast, or a chill reset. Post-trip surveys gather candid feedback plus testimonials the client can reuse internally, giving the transportation line item long-tail value. When riders feel seen at every touchpoint, the charter becomes part of the story instead of just a shuttle.\n\nIf you want this level of rigor for your own how early should you book? lead time by season & vehicle, tap the Bus2Ride concierge team and we will adapt the playbook to your city. We can collaborate directly with venues, production partners, hotels, or corporate travel managers and share our dashboards so everyone watches the same KPIs. Send a quick brief to info@bus2ride.com or call (888) 535-2566, and we will workshop route ideas, budgets, and backup plans in the first conversation. From there we lock in the exact fleet mix, staffing model, and amenity set that makes your brand, family, or fan base feel unstoppable.",
    "wordCount": 878,
    "thumbnail_url": "blog/How Early To Book.jpg",
    "published_at": "2025-01-20T12:00:00Z",
    "created_at": "2025-01-20T12:00:00Z",
    "updated_at": "2025-01-20T12:00:00Z",
    "keywords": [
      "booking",
      "timelines",
      "seasonality"
    ],
    "introHook": "Charter supply swings wildly between graduations, foliage tours, and holiday lights, so lead times must flex.",
    "planningFocus": "demand calendars, hold release policies, soft versus firm contracts",
    "logisticsFocus": "option expirations, payment triggers, comms workflow when fleets sell out",
    "amenitiesFocus": "vehicle swaps, upgrade ladders, seasonal decor storage",
    "budgetFocus": "early bird savings, surge multipliers, refundable deposits strategy",
    "experienceFocus": "transparent updates to hosts, alternative routing menus, white glove rebooking support"
  },
  {
    "id": "how-many-people-fit-seating-comfort-by-vehicle-type",
    "slug": "how-many-people-fit-seating-comfort-by-vehicle-type",
    "title": "How Many People Fit? Seating Comfort by Vehicle Type",
    "excerpt": "Stop cramming guests by matching body types, attire, and bag counts to realistic seat loads.",
    "content": "It is easy to romanticize how many people fit? seating comfort by vehicle type, but Capacity placards lie when gowns, camera gear, or mobility aids enter the chat. Bus2Ride treats every transport storyboard as a live operations document where each promise has an owner and a timestamp. We convert the directional keywords you keep repeating—Many, People, Fit, Seating—into routing guardrails, staffing ratios, and guest communications. That discipline keeps stakeholders aligned even when celebrity handlers, weather alerts, or late sponsor asks enter the chat at the last minute. By defining success through rider outcomes instead of vehicle specs, the rest of the planning stack becomes calmer and measurably more resilient. The goal is a weekend or single-night move that still feels effortless to guests while your logistics brain knows every variable has a backup.\n\nPlanning begins weeks upstream with discovery calls, forms, and scouting drives anchored around attire mapping, bag math, sample floorplans with lounge clusters. We map each traveler persona against the run of show so no one is surprised by attire changes, ADA requirements, or last minute VIP arrivals. Our producers draft layered itineraries that explain who greets whom, which curb is primary versus fallback, and what copy needs to be printed for signage. That documentation lets executives, wedding planners, campus staff, or brand teams sign off quickly because they can see the downstream effect of every choice. We also log no-go rules—the songs that must play, the neighborhoods to avoid, the shots the photographer is chasing—so host energy stays protected. When the planning stack reaches that clarity, even complex capacity, comfort, vehicles programs feel approachable.\n\nLogistics rehearsal focuses on staggered boarding, garment rack installs, luggage sprinter companions and the unglamorous tasks that actually preserve timelines. We confirm permits, credential needs, and staging pads with photos, measurements, and contacts so the driver handshake is more than a blind guess. Dispatch receives scenario scripts for weather, traffic gridlock, or celebrity security tweaks, and we mirror those scripts for the host team. Every loop has a dwell budget, fuel plan, restroom strategy, and spare vehicle logic documented in plain English. Because our on-site captains have direct radio or WhatsApp channels with chauffeurs, we can pulse information before a delay becomes a stall. That muscle memory turns potential chaos into small course corrections riders never notice.\n\nAmenities are curated intentionally instead of sprinkled randomly, with the spotlight on seat width comparisons, ottoman add ons, privacy dividers. We compare rider avatars against cabin layouts to decide where hydration stations, photo props, vow cards, or merch drops should live. Hosts receive a diagram that labels every comfort touch so they know what to hype on the mic, what to protect from overuse, and when to refresh each zone. When a vehicle swap happens, our amenity trunks and digital signage kits move too, which keeps the vibe consistent. We also script how chauffeurs or onboard concierges introduce the upgrades so the spend feels premium rather than gimmicky. Done right, the amenities quietly accelerate boarding, encourage social sharing, and keep the story cohesive from stop to stop.\n\nBudget modeling is transparent because we tie every dollar to a measurable constraint, especially around per vehicle efficiency, second shuttle triggers, rider upgrade pathways. Finance leaders see the decision matrix that compares doing nothing, DIY attempts, or hiring the operator to handle it turnkey. We highlight the costs of failure—injury claims, overtime spirals, missed sponsorship impressions—so approvals feel logical, not emotional. During build-out we log which lines are flexible and which are sacred, making it easier to pivot if the group size or routing changes. Deposits, milestone payments, and gratuity plans are stored in a single tracker to prevent the dreaded text chain of “who still owes what.” With that clarity, stakeholders stay calm even when the scope evolves because they understand the tradeoffs.\n\nExperience design pulls everything together with spacious photo ops, surprise seat gifts, satisfaction surveys that mention comfort specifically so guests feel guided instead of herded. We coach emcees, chauffeurs, and onboard crew on language that is inclusive, celebratory, and sensitive to the group’s culture. Live comms go out through SMS, WhatsApp, and QR-enabled microsites so riders always know where to stand, what is next, and who to text for help. Our media team stages photo or video beats that match the narrative arc, whether that is a reveal moment, a toast, or a chill reset. Post-trip surveys gather candid feedback plus testimonials the client can reuse internally, giving the transportation line item long-tail value. When riders feel seen at every touchpoint, the charter becomes part of the story instead of just a shuttle.\n\nIf you want this level of rigor for your own how many people fit? seating comfort by vehicle type, tap the Bus2Ride concierge team and we will adapt the playbook to your city. We can collaborate directly with venues, production partners, hotels, or corporate travel managers and share our dashboards so everyone watches the same KPIs. Send a quick brief to info@bus2ride.com or call (888) 535-2566, and we will workshop route ideas, budgets, and backup plans in the first conversation. From there we lock in the exact fleet mix, staffing model, and amenity set that makes your brand, family, or fan base feel unstoppable.",
    "wordCount": 872,
    "thumbnail_url": "blog/How Many Fit.jpg",
    "published_at": "2025-01-21T12:00:00Z",
    "created_at": "2025-01-21T12:00:00Z",
    "updated_at": "2025-01-21T12:00:00Z",
    "keywords": [
      "capacity",
      "comfort",
      "vehicles"
    ],
    "introHook": "Capacity placards lie when gowns, camera gear, or mobility aids enter the chat.",
    "planningFocus": "attire mapping, bag math, sample floorplans with lounge clusters",
    "logisticsFocus": "staggered boarding, garment rack installs, luggage sprinter companions",
    "amenitiesFocus": "seat width comparisons, ottoman add ons, privacy dividers",
    "budgetFocus": "per vehicle efficiency, second shuttle triggers, rider upgrade pathways",
    "experienceFocus": "spacious photo ops, surprise seat gifts, satisfaction surveys that mention comfort specifically"
  },
  {
    "id": "how-to-read-a-quote-hourly-vs-flat-rate-vs-fuel-service-fees",
    "slug": "how-to-read-a-quote-hourly-vs-flat-rate-vs-fuel-service-fees",
    "title": "How to Read a Quote: Hourly vs Flat Rate vs Fees",
    "excerpt": "Decode charter quotes so finance teams see the logic behind overtime, fuel, and service charges.",
    "content": "It is easy to romanticize how to read a quote: hourly vs flat rate vs fees, but If you cannot explain the fine print, your stakeholders will assume the operator padded the invoice. Bus2Ride treats every transport storyboard as a live operations document where each promise has an owner and a timestamp. We convert the directional keywords you keep repeating—Read, Quote, Hourly, Flat—into routing guardrails, staffing ratios, and guest communications. That discipline keeps stakeholders aligned even when celebrity handlers, weather alerts, or late sponsor asks enter the chat at the last minute. By defining success through rider outcomes instead of vehicle specs, the rest of the planning stack becomes calmer and measurably more resilient. The goal is a weekend or single-night move that still feels effortless to guests while your logistics brain knows every variable has a backup.\n\nPlanning begins weeks upstream with discovery calls, forms, and scouting drives anchored around apples to apples comparison docs, question logs, escalation timelines. We map each traveler persona against the run of show so no one is surprised by attire changes, ADA requirements, or last minute VIP arrivals. Our producers draft layered itineraries that explain who greets whom, which curb is primary versus fallback, and what copy needs to be printed for signage. That documentation lets executives, wedding planners, campus staff, or brand teams sign off quickly because they can see the downstream effect of every choice. We also log no-go rules—the songs that must play, the neighborhoods to avoid, the shots the photographer is chasing—so host energy stays protected. When the planning stack reaches that clarity, even complex quotes, budget, finance programs feel approachable.\n\nLogistics rehearsal focuses on deadhead calculations, duty hour rules, turnaround factors baked into pricing and the unglamorous tasks that actually preserve timelines. We confirm permits, credential needs, and staging pads with photos, measurements, and contacts so the driver handshake is more than a blind guess. Dispatch receives scenario scripts for weather, traffic gridlock, or celebrity security tweaks, and we mirror those scripts for the host team. Every loop has a dwell budget, fuel plan, restroom strategy, and spare vehicle logic documented in plain English. Because our on-site captains have direct radio or WhatsApp channels with chauffeurs, we can pulse information before a delay becomes a stall. That muscle memory turns potential chaos into small course corrections riders never notice.\n\nAmenities are curated intentionally instead of sprinkled randomly, with the spotlight on line item notes for host staffing, tech packages, decor labor. We compare rider avatars against cabin layouts to decide where hydration stations, photo props, vow cards, or merch drops should live. Hosts receive a diagram that labels every comfort touch so they know what to hype on the mic, what to protect from overuse, and when to refresh each zone. When a vehicle swap happens, our amenity trunks and digital signage kits move too, which keeps the vibe consistent. We also script how chauffeurs or onboard concierges introduce the upgrades so the spend feels premium rather than gimmicky. Done right, the amenities quietly accelerate boarding, encourage social sharing, and keep the story cohesive from stop to stop.\n\nBudget modeling is transparent because we tie every dollar to a measurable constraint, especially around fuel float models, gratuity policies, surcharge negotiation tactics. Finance leaders see the decision matrix that compares doing nothing, DIY attempts, or hiring the operator to handle it turnkey. We highlight the costs of failure—injury claims, overtime spirals, missed sponsorship impressions—so approvals feel logical, not emotional. During build-out we log which lines are flexible and which are sacred, making it easier to pivot if the group size or routing changes. Deposits, milestone payments, and gratuity plans are stored in a single tracker to prevent the dreaded text chain of “who still owes what.” With that clarity, stakeholders stay calm even when the scope evolves because they understand the tradeoffs.\n\nExperience design pulls everything together with finance friendly summaries, approval workflows, archive folders for audit season so guests feel guided instead of herded. We coach emcees, chauffeurs, and onboard crew on language that is inclusive, celebratory, and sensitive to the group’s culture. Live comms go out through SMS, WhatsApp, and QR-enabled microsites so riders always know where to stand, what is next, and who to text for help. Our media team stages photo or video beats that match the narrative arc, whether that is a reveal moment, a toast, or a chill reset. Post-trip surveys gather candid feedback plus testimonials the client can reuse internally, giving the transportation line item long-tail value. When riders feel seen at every touchpoint, the charter becomes part of the story instead of just a shuttle.\n\nIf you want this level of rigor for your own how to read a quote: hourly vs flat rate vs fees, tap the Bus2Ride concierge team and we will adapt the playbook to your city. We can collaborate directly with venues, production partners, hotels, or corporate travel managers and share our dashboards so everyone watches the same KPIs. Send a quick brief to info@bus2ride.com or call (888) 535-2566, and we will workshop route ideas, budgets, and backup plans in the first conversation. From there we lock in the exact fleet mix, staffing model, and amenity set that makes your brand, family, or fan base feel unstoppable.",
    "wordCount": 880,
    "thumbnail_url": "blog/How Read A Quote.jpg",
    "published_at": "2025-01-22T12:00:00Z",
    "created_at": "2025-01-22T12:00:00Z",
    "updated_at": "2025-01-22T12:00:00Z",
    "keywords": [
      "quotes",
      "budget",
      "finance"
    ],
    "introHook": "If you cannot explain the fine print, your stakeholders will assume the operator padded the invoice.",
    "planningFocus": "apples to apples comparison docs, question logs, escalation timelines",
    "logisticsFocus": "deadhead calculations, duty hour rules, turnaround factors baked into pricing",
    "amenitiesFocus": "line item notes for host staffing, tech packages, decor labor",
    "budgetFocus": "fuel float models, gratuity policies, surcharge negotiation tactics",
    "experienceFocus": "finance friendly summaries, approval workflows, archive folders for audit season"
  },
  {
    "id": "limo-vs-suv-vs-black-car-which-looks-best-for-your-event",
    "slug": "limo-vs-suv-vs-black-car-which-looks-best-for-your-event",
    "title": "Limo vs SUV vs Black Car: Which Looks Best?",
    "excerpt": "Match vehicle silhouettes to dress codes, paparazzi walls, and venue porte-cocheres.",
    "content": "It is easy to romanticize limo vs suv vs black car: which looks best?, but Visual impact matters, but so do headroom, door swing, and carpet-friendly tire tracks. Bus2Ride treats every transport storyboard as a live operations document where each promise has an owner and a timestamp. We convert the directional keywords you keep repeating—Limo, Suv, Black, Car—into routing guardrails, staffing ratios, and guest communications. That discipline keeps stakeholders aligned even when celebrity handlers, weather alerts, or late sponsor asks enter the chat at the last minute. By defining success through rider outcomes instead of vehicle specs, the rest of the planning stack becomes calmer and measurably more resilient. The goal is a weekend or single-night move that still feels effortless to guests while your logistics brain knows every variable has a backup.\n\nPlanning begins weeks upstream with discovery calls, forms, and scouting drives anchored around style boards, arrival run of show, host mic scripts for staging reveals. We map each traveler persona against the run of show so no one is surprised by attire changes, ADA requirements, or last minute VIP arrivals. Our producers draft layered itineraries that explain who greets whom, which curb is primary versus fallback, and what copy needs to be printed for signage. That documentation lets executives, wedding planners, campus staff, or brand teams sign off quickly because they can see the downstream effect of every choice. We also log no-go rules—the songs that must play, the neighborhoods to avoid, the shots the photographer is chasing—so host energy stays protected. When the planning stack reaches that clarity, even complex limousine, SUV, style programs feel approachable.\n\nLogistics rehearsal focuses on valet briefings, photo pit placement, rotation timing so vehicles stay spotless and the unglamorous tasks that actually preserve timelines. We confirm permits, credential needs, and staging pads with photos, measurements, and contacts so the driver handshake is more than a blind guess. Dispatch receives scenario scripts for weather, traffic gridlock, or celebrity security tweaks, and we mirror those scripts for the host team. Every loop has a dwell budget, fuel plan, restroom strategy, and spare vehicle logic documented in plain English. Because our on-site captains have direct radio or WhatsApp channels with chauffeurs, we can pulse information before a delay becomes a stall. That muscle memory turns potential chaos into small course corrections riders never notice.\n\nAmenities are curated intentionally instead of sprinkled randomly, with the spotlight on bar layouts, infotainment presets, privacy partitions tailored to the moment. We compare rider avatars against cabin layouts to decide where hydration stations, photo props, vow cards, or merch drops should live. Hosts receive a diagram that labels every comfort touch so they know what to hype on the mic, what to protect from overuse, and when to refresh each zone. When a vehicle swap happens, our amenity trunks and digital signage kits move too, which keeps the vibe consistent. We also script how chauffeurs or onboard concierges introduce the upgrades so the spend feels premium rather than gimmicky. Done right, the amenities quietly accelerate boarding, encourage social sharing, and keep the story cohesive from stop to stop.\n\nBudget modeling is transparent because we tie every dollar to a measurable constraint, especially around hybrid fleets, minimal hour commitments, swap fees when rain forces changes. Finance leaders see the decision matrix that compares doing nothing, DIY attempts, or hiring the operator to handle it turnkey. We highlight the costs of failure—injury claims, overtime spirals, missed sponsorship impressions—so approvals feel logical, not emotional. During build-out we log which lines are flexible and which are sacred, making it easier to pivot if the group size or routing changes. Deposits, milestone payments, and gratuity plans are stored in a single tracker to prevent the dreaded text chain of “who still owes what.” With that clarity, stakeholders stay calm even when the scope evolves because they understand the tradeoffs.\n\nExperience design pulls everything together with slow roll entrances, drone coverage, text alerts that cue photographers so guests feel guided instead of herded. We coach emcees, chauffeurs, and onboard crew on language that is inclusive, celebratory, and sensitive to the group’s culture. Live comms go out through SMS, WhatsApp, and QR-enabled microsites so riders always know where to stand, what is next, and who to text for help. Our media team stages photo or video beats that match the narrative arc, whether that is a reveal moment, a toast, or a chill reset. Post-trip surveys gather candid feedback plus testimonials the client can reuse internally, giving the transportation line item long-tail value. When riders feel seen at every touchpoint, the charter becomes part of the story instead of just a shuttle.\n\nIf you want this level of rigor for your own limo vs suv vs black car: which looks best?, tap the Bus2Ride concierge team and we will adapt the playbook to your city. We can collaborate directly with venues, production partners, hotels, or corporate travel managers and share our dashboards so everyone watches the same KPIs. Send a quick brief to info@bus2ride.com or call (888) 535-2566, and we will workshop route ideas, budgets, and backup plans in the first conversation. From there we lock in the exact fleet mix, staffing model, and amenity set that makes your brand, family, or fan base feel unstoppable.",
    "wordCount": 880,
    "thumbnail_url": "blog/Limo Versus Suv.jpg",
    "published_at": "2025-01-23T12:00:00Z",
    "created_at": "2025-01-23T12:00:00Z",
    "updated_at": "2025-01-23T12:00:00Z",
    "keywords": [
      "limousine",
      "SUV",
      "style"
    ],
    "introHook": "Visual impact matters, but so do headroom, door swing, and carpet-friendly tire tracks.",
    "planningFocus": "style boards, arrival run of show, host mic scripts for staging reveals",
    "logisticsFocus": "valet briefings, photo pit placement, rotation timing so vehicles stay spotless",
    "amenitiesFocus": "bar layouts, infotainment presets, privacy partitions tailored to the moment",
    "budgetFocus": "hybrid fleets, minimal hour commitments, swap fees when rain forces changes",
    "experienceFocus": "slow roll entrances, drone coverage, text alerts that cue photographers"
  },
  {
    "id": "luxury-vs-standard-limo-what-you-actually-get-for-the-price",
    "slug": "luxury-vs-standard-limo-what-you-actually-get-for-the-price",
    "title": "Luxury vs Standard Limo: What You Actually Get",
    "excerpt": "Understand which upgrades justify the premium so you know when to splurge or save.",
    "content": "It is easy to romanticize luxury vs standard limo: what you actually get, but Not all stretch limos are equal; some hide thirty pin connectors while others stream 4K cabin feeds. Bus2Ride treats every transport storyboard as a live operations document where each promise has an owner and a timestamp. We convert the directional keywords you keep repeating—Luxury, Standard, Limo, What—into routing guardrails, staffing ratios, and guest communications. That discipline keeps stakeholders aligned even when celebrity handlers, weather alerts, or late sponsor asks enter the chat at the last minute. By defining success through rider outcomes instead of vehicle specs, the rest of the planning stack becomes calmer and measurably more resilient. The goal is a weekend or single-night move that still feels effortless to guests while your logistics brain knows every variable has a backup.\n\nPlanning begins weeks upstream with discovery calls, forms, and scouting drives anchored around client vision interviews, shot lists, mood boards matched to trim packages. We map each traveler persona against the run of show so no one is surprised by attire changes, ADA requirements, or last minute VIP arrivals. Our producers draft layered itineraries that explain who greets whom, which curb is primary versus fallback, and what copy needs to be printed for signage. That documentation lets executives, wedding planners, campus staff, or brand teams sign off quickly because they can see the downstream effect of every choice. We also log no-go rules—the songs that must play, the neighborhoods to avoid, the shots the photographer is chasing—so host energy stays protected. When the planning stack reaches that clarity, even complex luxury, limousine, amenities programs feel approachable.\n\nLogistics rehearsal focuses on fleet inspection days, keyless entry backups, two way comms tests and the unglamorous tasks that actually preserve timelines. We confirm permits, credential needs, and staging pads with photos, measurements, and contacts so the driver handshake is more than a blind guess. Dispatch receives scenario scripts for weather, traffic gridlock, or celebrity security tweaks, and we mirror those scripts for the host team. Every loop has a dwell budget, fuel plan, restroom strategy, and spare vehicle logic documented in plain English. Because our on-site captains have direct radio or WhatsApp channels with chauffeurs, we can pulse information before a delay becomes a stall. That muscle memory turns potential chaos into small course corrections riders never notice.\n\nAmenities are curated intentionally instead of sprinkled randomly, with the spotlight on starlight ceilings, glassware tiers, fragrance programs. We compare rider avatars against cabin layouts to decide where hydration stations, photo props, vow cards, or merch drops should live. Hosts receive a diagram that labels every comfort touch so they know what to hype on the mic, what to protect from overuse, and when to refresh each zone. When a vehicle swap happens, our amenity trunks and digital signage kits move too, which keeps the vibe consistent. We also script how chauffeurs or onboard concierges introduce the upgrades so the spend feels premium rather than gimmicky. Done right, the amenities quietly accelerate boarding, encourage social sharing, and keep the story cohesive from stop to stop.\n\nBudget modeling is transparent because we tie every dollar to a measurable constraint, especially around upgrade ladders, depreciation aware pricing, bundle deals for multi day rentals. Finance leaders see the decision matrix that compares doing nothing, DIY attempts, or hiring the operator to handle it turnkey. We highlight the costs of failure—injury claims, overtime spirals, missed sponsorship impressions—so approvals feel logical, not emotional. During build-out we log which lines are flexible and which are sacred, making it easier to pivot if the group size or routing changes. Deposits, milestone payments, and gratuity plans are stored in a single tracker to prevent the dreaded text chain of “who still owes what.” With that clarity, stakeholders stay calm even when the scope evolves because they understand the tradeoffs.\n\nExperience design pulls everything together with concierge briefings, amenity labels, handwritten welcome cards from the chauffeur so guests feel guided instead of herded. We coach emcees, chauffeurs, and onboard crew on language that is inclusive, celebratory, and sensitive to the group’s culture. Live comms go out through SMS, WhatsApp, and QR-enabled microsites so riders always know where to stand, what is next, and who to text for help. Our media team stages photo or video beats that match the narrative arc, whether that is a reveal moment, a toast, or a chill reset. Post-trip surveys gather candid feedback plus testimonials the client can reuse internally, giving the transportation line item long-tail value. When riders feel seen at every touchpoint, the charter becomes part of the story instead of just a shuttle.\n\nIf you want this level of rigor for your own luxury vs standard limo: what you actually get, tap the Bus2Ride concierge team and we will adapt the playbook to your city. We can collaborate directly with venues, production partners, hotels, or corporate travel managers and share our dashboards so everyone watches the same KPIs. Send a quick brief to info@bus2ride.com or call (888) 535-2566, and we will workshop route ideas, budgets, and backup plans in the first conversation. From there we lock in the exact fleet mix, staffing model, and amenity set that makes your brand, family, or fan base feel unstoppable.",
    "wordCount": 876,
    "thumbnail_url": "blog/Luxury Upgrades.jpg",
    "published_at": "2025-01-24T12:00:00Z",
    "created_at": "2025-01-24T12:00:00Z",
    "updated_at": "2025-01-24T12:00:00Z",
    "keywords": [
      "luxury",
      "limousine",
      "amenities"
    ],
    "introHook": "Not all stretch limos are equal; some hide thirty pin connectors while others stream 4K cabin feeds.",
    "planningFocus": "client vision interviews, shot lists, mood boards matched to trim packages",
    "logisticsFocus": "fleet inspection days, keyless entry backups, two way comms tests",
    "amenitiesFocus": "starlight ceilings, glassware tiers, fragrance programs",
    "budgetFocus": "upgrade ladders, depreciation aware pricing, bundle deals for multi day rentals",
    "experienceFocus": "concierge briefings, amenity labels, handwritten welcome cards from the chauffeur"
  },
  {
    "id": "neighborhood-pickup-strategy-for-big-groups",
    "slug": "neighborhood-pickup-strategy-for-big-groups",
    "title": "Neighborhood Pickup Strategy for Big Groups",
    "excerpt": "Cut late arrivals by clustering addresses, staging micro hubs, and communicating like a rideshare fleet.",
    "content": "It is easy to romanticize neighborhood pickup strategy for big groups, but Door-to-door promises sound nice until your driver spends fifty minutes tracing cul-de-sacs. Bus2Ride treats every transport storyboard as a live operations document where each promise has an owner and a timestamp. We convert the directional keywords you keep repeating—Neighborhood, Pickup, Strategy, Big—into routing guardrails, staffing ratios, and guest communications. That discipline keeps stakeholders aligned even when celebrity handlers, weather alerts, or late sponsor asks enter the chat at the last minute. By defining success through rider outcomes instead of vehicle specs, the rest of the planning stack becomes calmer and measurably more resilient. The goal is a weekend or single-night move that still feels effortless to guests while your logistics brain knows every variable has a backup.\n\nPlanning begins weeks upstream with discovery calls, forms, and scouting drives anchored around heat maps of riders, hub assignments, SMS templates for each wave. We map each traveler persona against the run of show so no one is surprised by attire changes, ADA requirements, or last minute VIP arrivals. Our producers draft layered itineraries that explain who greets whom, which curb is primary versus fallback, and what copy needs to be printed for signage. That documentation lets executives, wedding planners, campus staff, or brand teams sign off quickly because they can see the downstream effect of every choice. We also log no-go rules—the songs that must play, the neighborhoods to avoid, the shots the photographer is chasing—so host energy stays protected. When the planning stack reaches that clarity, even complex pickups, routing, groups programs feel approachable.\n\nLogistics rehearsal focuses on shuttle captains, cone kits, secondary streets for turnaround space and the unglamorous tasks that actually preserve timelines. We confirm permits, credential needs, and staging pads with photos, measurements, and contacts so the driver handshake is more than a blind guess. Dispatch receives scenario scripts for weather, traffic gridlock, or celebrity security tweaks, and we mirror those scripts for the host team. Every loop has a dwell budget, fuel plan, restroom strategy, and spare vehicle logic documented in plain English. Because our on-site captains have direct radio or WhatsApp channels with chauffeurs, we can pulse information before a delay becomes a stall. That muscle memory turns potential chaos into small course corrections riders never notice.\n\nAmenities are curated intentionally instead of sprinkled randomly, with the spotlight on check in signage, welcome beverages at hubs, stroller or luggage corrals. We compare rider avatars against cabin layouts to decide where hydration stations, photo props, vow cards, or merch drops should live. Hosts receive a diagram that labels every comfort touch so they know what to hype on the mic, what to protect from overuse, and when to refresh each zone. When a vehicle swap happens, our amenity trunks and digital signage kits move too, which keeps the vibe consistent. We also script how chauffeurs or onboard concierges introduce the upgrades so the spend feels premium rather than gimmicky. Done right, the amenities quietly accelerate boarding, encourage social sharing, and keep the story cohesive from stop to stop.\n\nBudget modeling is transparent because we tie every dollar to a measurable constraint, especially around micro shuttle rentals, overtime avoidance math, rider opt in incentives. Finance leaders see the decision matrix that compares doing nothing, DIY attempts, or hiring the operator to handle it turnkey. We highlight the costs of failure—injury claims, overtime spirals, missed sponsorship impressions—so approvals feel logical, not emotional. During build-out we log which lines are flexible and which are sacred, making it easier to pivot if the group size or routing changes. Deposits, milestone payments, and gratuity plans are stored in a single tracker to prevent the dreaded text chain of “who still owes what.” With that clarity, stakeholders stay calm even when the scope evolves because they understand the tradeoffs.\n\nExperience design pulls everything together with live pickup trackers, concierge hotlines, photo moments at each neighborhood hub so guests feel guided instead of herded. We coach emcees, chauffeurs, and onboard crew on language that is inclusive, celebratory, and sensitive to the group’s culture. Live comms go out through SMS, WhatsApp, and QR-enabled microsites so riders always know where to stand, what is next, and who to text for help. Our media team stages photo or video beats that match the narrative arc, whether that is a reveal moment, a toast, or a chill reset. Post-trip surveys gather candid feedback plus testimonials the client can reuse internally, giving the transportation line item long-tail value. When riders feel seen at every touchpoint, the charter becomes part of the story instead of just a shuttle.\n\nIf you want this level of rigor for your own neighborhood pickup strategy for big groups, tap the Bus2Ride concierge team and we will adapt the playbook to your city. We can collaborate directly with venues, production partners, hotels, or corporate travel managers and share our dashboards so everyone watches the same KPIs. Send a quick brief to info@bus2ride.com or call (888) 535-2566, and we will workshop route ideas, budgets, and backup plans in the first conversation. From there we lock in the exact fleet mix, staffing model, and amenity set that makes your brand, family, or fan base feel unstoppable.",
    "wordCount": 871,
    "thumbnail_url": "blog/Neighborhood.jpg",
    "published_at": "2025-01-25T12:00:00Z",
    "created_at": "2025-01-25T12:00:00Z",
    "updated_at": "2025-01-25T12:00:00Z",
    "keywords": [
      "pickups",
      "routing",
      "groups"
    ],
    "introHook": "Door-to-door promises sound nice until your driver spends fifty minutes tracing cul-de-sacs.",
    "planningFocus": "heat maps of riders, hub assignments, SMS templates for each wave",
    "logisticsFocus": "shuttle captains, cone kits, secondary streets for turnaround space",
    "amenitiesFocus": "check in signage, welcome beverages at hubs, stroller or luggage corrals",
    "budgetFocus": "micro shuttle rentals, overtime avoidance math, rider opt in incentives",
    "experienceFocus": "live pickup trackers, concierge hotlines, photo moments at each neighborhood hub"
  },
  {
    "id": "party-bus-pricing-101",
    "slug": "party-bus-pricing-101",
    "title": "Party Bus Pricing 101",
    "excerpt": "Break down hourly minimums, mileage, cleaning fees, and seasonal surges so your quote lands smoothly.",
    "content": "It is easy to romanticize party bus pricing 101, but The same 30 passenger bus can cost half as much on a Sunday brunch compared to homecoming weekend. Bus2Ride treats every transport storyboard as a live operations document where each promise has an owner and a timestamp. We convert the directional keywords you keep repeating—Party, Bus, Pricing, 101—into routing guardrails, staffing ratios, and guest communications. That discipline keeps stakeholders aligned even when celebrity handlers, weather alerts, or late sponsor asks enter the chat at the last minute. By defining success through rider outcomes instead of vehicle specs, the rest of the planning stack becomes calmer and measurably more resilient. The goal is a weekend or single-night move that still feels effortless to guests while your logistics brain knows every variable has a backup.\n\nPlanning begins weeks upstream with discovery calls, forms, and scouting drives anchored around timeline locks, stop counts, variance scenarios for late-night add ons. We map each traveler persona against the run of show so no one is surprised by attire changes, ADA requirements, or last minute VIP arrivals. Our producers draft layered itineraries that explain who greets whom, which curb is primary versus fallback, and what copy needs to be printed for signage. That documentation lets executives, wedding planners, campus staff, or brand teams sign off quickly because they can see the downstream effect of every choice. We also log no-go rules—the songs that must play, the neighborhoods to avoid, the shots the photographer is chasing—so host energy stays protected. When the planning stack reaches that clarity, even complex party bus, pricing, budget programs feel approachable.\n\nLogistics rehearsal focuses on fuel burn, driver swaps, cleaning turnarounds between charters and the unglamorous tasks that actually preserve timelines. We confirm permits, credential needs, and staging pads with photos, measurements, and contacts so the driver handshake is more than a blind guess. Dispatch receives scenario scripts for weather, traffic gridlock, or celebrity security tweaks, and we mirror those scripts for the host team. Every loop has a dwell budget, fuel plan, restroom strategy, and spare vehicle logic documented in plain English. Because our on-site captains have direct radio or WhatsApp channels with chauffeurs, we can pulse information before a delay becomes a stall. That muscle memory turns potential chaos into small course corrections riders never notice.\n\nAmenities are curated intentionally instead of sprinkled randomly, with the spotlight on light show upgrades, host staffing, prop rentals with security deposits. We compare rider avatars against cabin layouts to decide where hydration stations, photo props, vow cards, or merch drops should live. Hosts receive a diagram that labels every comfort touch so they know what to hype on the mic, what to protect from overuse, and when to refresh each zone. When a vehicle swap happens, our amenity trunks and digital signage kits move too, which keeps the vibe consistent. We also script how chauffeurs or onboard concierges introduce the upgrades so the spend feels premium rather than gimmicky. Done right, the amenities quietly accelerate boarding, encourage social sharing, and keep the story cohesive from stop to stop.\n\nBudget modeling is transparent because we tie every dollar to a measurable constraint, especially around hourly ladders, gratuity norms, damage waiver math. Finance leaders see the decision matrix that compares doing nothing, DIY attempts, or hiring the operator to handle it turnkey. We highlight the costs of failure—injury claims, overtime spirals, missed sponsorship impressions—so approvals feel logical, not emotional. During build-out we log which lines are flexible and which are sacred, making it easier to pivot if the group size or routing changes. Deposits, milestone payments, and gratuity plans are stored in a single tracker to prevent the dreaded text chain of “who still owes what.” With that clarity, stakeholders stay calm even when the scope evolves because they understand the tradeoffs.\n\nExperience design pulls everything together with transparent receipts, QR code tipping, satisfaction checkpoints mid-route so guests feel guided instead of herded. We coach emcees, chauffeurs, and onboard crew on language that is inclusive, celebratory, and sensitive to the group’s culture. Live comms go out through SMS, WhatsApp, and QR-enabled microsites so riders always know where to stand, what is next, and who to text for help. Our media team stages photo or video beats that match the narrative arc, whether that is a reveal moment, a toast, or a chill reset. Post-trip surveys gather candid feedback plus testimonials the client can reuse internally, giving the transportation line item long-tail value. When riders feel seen at every touchpoint, the charter becomes part of the story instead of just a shuttle.\n\nIf you want this level of rigor for your own party bus pricing 101, tap the Bus2Ride concierge team and we will adapt the playbook to your city. We can collaborate directly with venues, production partners, hotels, or corporate travel managers and share our dashboards so everyone watches the same KPIs. Send a quick brief to info@bus2ride.com or call (888) 535-2566, and we will workshop route ideas, budgets, and backup plans in the first conversation. From there we lock in the exact fleet mix, staffing model, and amenity set that makes your brand, family, or fan base feel unstoppable.",
    "wordCount": 865,
    "thumbnail_url": "blog/Party Bus Pricing.jpg",
    "published_at": "2025-01-26T12:00:00Z",
    "created_at": "2025-01-26T12:00:00Z",
    "updated_at": "2025-01-26T12:00:00Z",
    "keywords": [
      "party bus",
      "pricing",
      "budget"
    ],
    "introHook": "The same 30 passenger bus can cost half as much on a Sunday brunch compared to homecoming weekend.",
    "planningFocus": "timeline locks, stop counts, variance scenarios for late-night add ons",
    "logisticsFocus": "fuel burn, driver swaps, cleaning turnarounds between charters",
    "amenitiesFocus": "light show upgrades, host staffing, prop rentals with security deposits",
    "budgetFocus": "hourly ladders, gratuity norms, damage waiver math",
    "experienceFocus": "transparent receipts, QR code tipping, satisfaction checkpoints mid-route"
  },
  {
    "id": "photogenic-rides-interior-lighting-photo-stop-ideas",
    "slug": "photogenic-rides-interior-lighting-photo-stop-ideas",
    "title": "Photogenic Rides: Interior Lighting & Photo Stop Ideas",
    "excerpt": "Engineer camera-friendly lighting and scenic layovers so the vehicle becomes part of the content strategy.",
    "content": "It is easy to romanticize photogenic rides: interior lighting & photo stop ideas, but If you want viral clips, you need diffusion, power drops, and permissions lined up, not just vibes. Bus2Ride treats every transport storyboard as a live operations document where each promise has an owner and a timestamp. We convert the directional keywords you keep repeating—Photogenic, Rides, Interior, Lighting—into routing guardrails, staffing ratios, and guest communications. That discipline keeps stakeholders aligned even when celebrity handlers, weather alerts, or late sponsor asks enter the chat at the last minute. By defining success through rider outcomes instead of vehicle specs, the rest of the planning stack becomes calmer and measurably more resilient. The goal is a weekend or single-night move that still feels effortless to guests while your logistics brain knows every variable has a backup.\n\nPlanning begins weeks upstream with discovery calls, forms, and scouting drives anchored around shot lists, director walkthroughs, remote battery packs labeled per rig. We map each traveler persona against the run of show so no one is surprised by attire changes, ADA requirements, or last minute VIP arrivals. Our producers draft layered itineraries that explain who greets whom, which curb is primary versus fallback, and what copy needs to be printed for signage. That documentation lets executives, wedding planners, campus staff, or brand teams sign off quickly because they can see the downstream effect of every choice. We also log no-go rules—the songs that must play, the neighborhoods to avoid, the shots the photographer is chasing—so host energy stays protected. When the planning stack reaches that clarity, even complex photos, lighting, content programs feel approachable.\n\nLogistics rehearsal focuses on scouted turnouts, city film permits, rain backup shelters and the unglamorous tasks that actually preserve timelines. We confirm permits, credential needs, and staging pads with photos, measurements, and contacts so the driver handshake is more than a blind guess. Dispatch receives scenario scripts for weather, traffic gridlock, or celebrity security tweaks, and we mirror those scripts for the host team. Every loop has a dwell budget, fuel plan, restroom strategy, and spare vehicle logic documented in plain English. Because our on-site captains have direct radio or WhatsApp channels with chauffeurs, we can pulse information before a delay becomes a stall. That muscle memory turns potential chaos into small course corrections riders never notice.\n\nAmenities are curated intentionally instead of sprinkled randomly, with the spotlight on ring lights, neon word signs, stain resistant floors for confetti moments. We compare rider avatars against cabin layouts to decide where hydration stations, photo props, vow cards, or merch drops should live. Hosts receive a diagram that labels every comfort touch so they know what to hype on the mic, what to protect from overuse, and when to refresh each zone. When a vehicle swap happens, our amenity trunks and digital signage kits move too, which keeps the vibe consistent. We also script how chauffeurs or onboard concierges introduce the upgrades so the spend feels premium rather than gimmicky. Done right, the amenities quietly accelerate boarding, encourage social sharing, and keep the story cohesive from stop to stop.\n\nBudget modeling is transparent because we tie every dollar to a measurable constraint, especially around photographer retainers, lighting insurance, branded prop storage. Finance leaders see the decision matrix that compares doing nothing, DIY attempts, or hiring the operator to handle it turnkey. We highlight the costs of failure—injury claims, overtime spirals, missed sponsorship impressions—so approvals feel logical, not emotional. During build-out we log which lines are flexible and which are sacred, making it easier to pivot if the group size or routing changes. Deposits, milestone payments, and gratuity plans are stored in a single tracker to prevent the dreaded text chain of “who still owes what.” With that clarity, stakeholders stay calm even when the scope evolves because they understand the tradeoffs.\n\nExperience design pulls everything together with onboard photo directors, instant gallery delivery, sponsor-ready captions so guests feel guided instead of herded. We coach emcees, chauffeurs, and onboard crew on language that is inclusive, celebratory, and sensitive to the group’s culture. Live comms go out through SMS, WhatsApp, and QR-enabled microsites so riders always know where to stand, what is next, and who to text for help. Our media team stages photo or video beats that match the narrative arc, whether that is a reveal moment, a toast, or a chill reset. Post-trip surveys gather candid feedback plus testimonials the client can reuse internally, giving the transportation line item long-tail value. When riders feel seen at every touchpoint, the charter becomes part of the story instead of just a shuttle.\n\nIf you want this level of rigor for your own photogenic rides: interior lighting & photo stop ideas, tap the Bus2Ride concierge team and we will adapt the playbook to your city. We can collaborate directly with venues, production partners, hotels, or corporate travel managers and share our dashboards so everyone watches the same KPIs. Send a quick brief to info@bus2ride.com or call (888) 535-2566, and we will workshop route ideas, budgets, and backup plans in the first conversation. From there we lock in the exact fleet mix, staffing model, and amenity set that makes your brand, family, or fan base feel unstoppable.",
    "wordCount": 872,
    "thumbnail_url": "blog/Photogenic Stops.jpg",
    "published_at": "2025-01-27T12:00:00Z",
    "created_at": "2025-01-27T12:00:00Z",
    "updated_at": "2025-01-27T12:00:00Z",
    "keywords": [
      "photos",
      "lighting",
      "content"
    ],
    "introHook": "If you want viral clips, you need diffusion, power drops, and permissions lined up, not just vibes.",
    "planningFocus": "shot lists, director walkthroughs, remote battery packs labeled per rig",
    "logisticsFocus": "scouted turnouts, city film permits, rain backup shelters",
    "amenitiesFocus": "ring lights, neon word signs, stain resistant floors for confetti moments",
    "budgetFocus": "photographer retainers, lighting insurance, branded prop storage",
    "experienceFocus": "onboard photo directors, instant gallery delivery, sponsor-ready captions"
  },
  {
    "id": "safety-first-what-a-professional-chauffeur-does-differently",
    "slug": "safety-first-what-a-professional-chauffeur-does-differently",
    "title": "Safety First: What a Professional Chauffeur Does Differently",
    "excerpt": "Show riders the unseen discipline behind elite chauffeurs so they respect the process.",
    "content": "It is easy to romanticize safety first: what a professional chauffeur does differently, but The best chauffeurs obsess over mirrors, shoe polish, and pre-trip rituals that passengers rarely notice. Bus2Ride treats every transport storyboard as a live operations document where each promise has an owner and a timestamp. We convert the directional keywords you keep repeating—Safety, First, What, Professional—into routing guardrails, staffing ratios, and guest communications. That discipline keeps stakeholders aligned even when celebrity handlers, weather alerts, or late sponsor asks enter the chat at the last minute. By defining success through rider outcomes instead of vehicle specs, the rest of the planning stack becomes calmer and measurably more resilient. The goal is a weekend or single-night move that still feels effortless to guests while your logistics brain knows every variable has a backup.\n\nPlanning begins weeks upstream with discovery calls, forms, and scouting drives anchored around training ladders, certification tracking, scenario drills with dispatch. We map each traveler persona against the run of show so no one is surprised by attire changes, ADA requirements, or last minute VIP arrivals. Our producers draft layered itineraries that explain who greets whom, which curb is primary versus fallback, and what copy needs to be printed for signage. That documentation lets executives, wedding planners, campus staff, or brand teams sign off quickly because they can see the downstream effect of every choice. We also log no-go rules—the songs that must play, the neighborhoods to avoid, the shots the photographer is chasing—so host energy stays protected. When the planning stack reaches that clarity, even complex safety, chauffeur, training programs feel approachable.\n\nLogistics rehearsal focuses on defensive routes, fatigue monitoring, dual radio channels for redundancies and the unglamorous tasks that actually preserve timelines. We confirm permits, credential needs, and staging pads with photos, measurements, and contacts so the driver handshake is more than a blind guess. Dispatch receives scenario scripts for weather, traffic gridlock, or celebrity security tweaks, and we mirror those scripts for the host team. Every loop has a dwell budget, fuel plan, restroom strategy, and spare vehicle logic documented in plain English. Because our on-site captains have direct radio or WhatsApp channels with chauffeurs, we can pulse information before a delay becomes a stall. That muscle memory turns potential chaos into small course corrections riders never notice.\n\nAmenities are curated intentionally instead of sprinkled randomly, with the spotlight on concierge style door service, emergency kits, discreet med gear. We compare rider avatars against cabin layouts to decide where hydration stations, photo props, vow cards, or merch drops should live. Hosts receive a diagram that labels every comfort touch so they know what to hype on the mic, what to protect from overuse, and when to refresh each zone. When a vehicle swap happens, our amenity trunks and digital signage kits move too, which keeps the vibe consistent. We also script how chauffeurs or onboard concierges introduce the upgrades so the spend feels premium rather than gimmicky. Done right, the amenities quietly accelerate boarding, encourage social sharing, and keep the story cohesive from stop to stop.\n\nBudget modeling is transparent because we tie every dollar to a measurable constraint, especially around premium labor rates, retention bonuses, ongoing education stipends. Finance leaders see the decision matrix that compares doing nothing, DIY attempts, or hiring the operator to handle it turnkey. We highlight the costs of failure—injury claims, overtime spirals, missed sponsorship impressions—so approvals feel logical, not emotional. During build-out we log which lines are flexible and which are sacred, making it easier to pivot if the group size or routing changes. Deposits, milestone payments, and gratuity plans are stored in a single tracker to prevent the dreaded text chain of “who still owes what.” With that clarity, stakeholders stay calm even when the scope evolves because they understand the tradeoffs.\n\nExperience design pulls everything together with chauffeur bios, safety briefings, thank you programs that keep crews engaged so guests feel guided instead of herded. We coach emcees, chauffeurs, and onboard crew on language that is inclusive, celebratory, and sensitive to the group’s culture. Live comms go out through SMS, WhatsApp, and QR-enabled microsites so riders always know where to stand, what is next, and who to text for help. Our media team stages photo or video beats that match the narrative arc, whether that is a reveal moment, a toast, or a chill reset. Post-trip surveys gather candid feedback plus testimonials the client can reuse internally, giving the transportation line item long-tail value. When riders feel seen at every touchpoint, the charter becomes part of the story instead of just a shuttle.\n\nIf you want this level of rigor for your own safety first: what a professional chauffeur does differently, tap the Bus2Ride concierge team and we will adapt the playbook to your city. We can collaborate directly with venues, production partners, hotels, or corporate travel managers and share our dashboards so everyone watches the same KPIs. Send a quick brief to info@bus2ride.com or call (888) 535-2566, and we will workshop route ideas, budgets, and backup plans in the first conversation. From there we lock in the exact fleet mix, staffing model, and amenity set that makes your brand, family, or fan base feel unstoppable.",
    "wordCount": 871,
    "thumbnail_url": "blog/Safety.jpg",
    "published_at": "2025-01-28T12:00:00Z",
    "created_at": "2025-01-28T12:00:00Z",
    "updated_at": "2025-01-28T12:00:00Z",
    "keywords": [
      "safety",
      "chauffeur",
      "training"
    ],
    "introHook": "The best chauffeurs obsess over mirrors, shoe polish, and pre-trip rituals that passengers rarely notice.",
    "planningFocus": "training ladders, certification tracking, scenario drills with dispatch",
    "logisticsFocus": "defensive routes, fatigue monitoring, dual radio channels for redundancies",
    "amenitiesFocus": "concierge style door service, emergency kits, discreet med gear",
    "budgetFocus": "premium labor rates, retention bonuses, ongoing education stipends",
    "experienceFocus": "chauffeur bios, safety briefings, thank you programs that keep crews engaged"
  },
  {
    "id": "prom-night-safety-checklist-for-parents-teens",
    "slug": "prom-night-safety-checklist-for-parents-teens",
    "title": "Prom Night Safety Checklist for Parents & Teens",
    "excerpt": "Blend unforgettable prom entrances with curfews, check-ins, and sober monitors everyone trusts.",
    "content": "It is easy to romanticize prom night safety checklist for parents & teens, but Parents want a legal chain of custody while teens want sparkle, so we give both. Bus2Ride treats every transport storyboard as a live operations document where each promise has an owner and a timestamp. We convert the directional keywords you keep repeating—Prom, Night, Safety, Checklist—into routing guardrails, staffing ratios, and guest communications. That discipline keeps stakeholders aligned even when celebrity handlers, weather alerts, or late sponsor asks enter the chat at the last minute. By defining success through rider outcomes instead of vehicle specs, the rest of the planning stack becomes calmer and measurably more resilient. The goal is a weekend or single-night move that still feels effortless to guests while your logistics brain knows every variable has a backup.\n\nPlanning begins weeks upstream with discovery calls, forms, and scouting drives anchored around contract addendums, code word systems, parent orientation calls. We map each traveler persona against the run of show so no one is surprised by attire changes, ADA requirements, or last minute VIP arrivals. Our producers draft layered itineraries that explain who greets whom, which curb is primary versus fallback, and what copy needs to be printed for signage. That documentation lets executives, wedding planners, campus staff, or brand teams sign off quickly because they can see the downstream effect of every choice. We also log no-go rules—the songs that must play, the neighborhoods to avoid, the shots the photographer is chasing—so host energy stays protected. When the planning stack reaches that clarity, even complex prom, safety, teens programs feel approachable.\n\nLogistics rehearsal focuses on bag checks, route transparency, staggered returns for multiple schools and the unglamorous tasks that actually preserve timelines. We confirm permits, credential needs, and staging pads with photos, measurements, and contacts so the driver handshake is more than a blind guess. Dispatch receives scenario scripts for weather, traffic gridlock, or celebrity security tweaks, and we mirror those scripts for the host team. Every loop has a dwell budget, fuel plan, restroom strategy, and spare vehicle logic documented in plain English. Because our on-site captains have direct radio or WhatsApp channels with chauffeurs, we can pulse information before a delay becomes a stall. That muscle memory turns potential chaos into small course corrections riders never notice.\n\nAmenities are curated intentionally instead of sprinkled randomly, with the spotlight on mocktail bars, glam touch up kits, step and repeat backdrops. We compare rider avatars against cabin layouts to decide where hydration stations, photo props, vow cards, or merch drops should live. Hosts receive a diagram that labels every comfort touch so they know what to hype on the mic, what to protect from overuse, and when to refresh each zone. When a vehicle swap happens, our amenity trunks and digital signage kits move too, which keeps the vibe consistent. We also script how chauffeurs or onboard concierges introduce the upgrades so the spend feels premium rather than gimmicky. Done right, the amenities quietly accelerate boarding, encourage social sharing, and keep the story cohesive from stop to stop.\n\nBudget modeling is transparent because we tie every dollar to a measurable constraint, especially around shared charters, booster underwriting, security staffing costs. Finance leaders see the decision matrix that compares doing nothing, DIY attempts, or hiring the operator to handle it turnkey. We highlight the costs of failure—injury claims, overtime spirals, missed sponsorship impressions—so approvals feel logical, not emotional. During build-out we log which lines are flexible and which are sacred, making it easier to pivot if the group size or routing changes. Deposits, milestone payments, and gratuity plans are stored in a single tracker to prevent the dreaded text chain of “who still owes what.” With that clarity, stakeholders stay calm even when the scope evolves because they understand the tradeoffs.\n\nExperience design pulls everything together with live location pings, gratitude shoutouts, alumni mentors on board so guests feel guided instead of herded. We coach emcees, chauffeurs, and onboard crew on language that is inclusive, celebratory, and sensitive to the group’s culture. Live comms go out through SMS, WhatsApp, and QR-enabled microsites so riders always know where to stand, what is next, and who to text for help. Our media team stages photo or video beats that match the narrative arc, whether that is a reveal moment, a toast, or a chill reset. Post-trip surveys gather candid feedback plus testimonials the client can reuse internally, giving the transportation line item long-tail value. When riders feel seen at every touchpoint, the charter becomes part of the story instead of just a shuttle.\n\nIf you want this level of rigor for your own prom night safety checklist for parents & teens, tap the Bus2Ride concierge team and we will adapt the playbook to your city. We can collaborate directly with venues, production partners, hotels, or corporate travel managers and share our dashboards so everyone watches the same KPIs. Send a quick brief to info@bus2ride.com or call (888) 535-2566, and we will workshop route ideas, budgets, and backup plans in the first conversation. From there we lock in the exact fleet mix, staffing model, and amenity set that makes your brand, family, or fan base feel unstoppable.",
    "wordCount": 869,
    "thumbnail_url": "blog/Prom Safety.jpg",
    "published_at": "2025-01-29T12:00:00Z",
    "created_at": "2025-01-29T12:00:00Z",
    "updated_at": "2025-01-29T12:00:00Z",
    "keywords": [
      "prom",
      "safety",
      "teens"
    ],
    "introHook": "Parents want a legal chain of custody while teens want sparkle, so we give both.",
    "planningFocus": "contract addendums, code word systems, parent orientation calls",
    "logisticsFocus": "bag checks, route transparency, staggered returns for multiple schools",
    "amenitiesFocus": "mocktail bars, glam touch up kits, step and repeat backdrops",
    "budgetFocus": "shared charters, booster underwriting, security staffing costs",
    "experienceFocus": "live location pings, gratitude shoutouts, alumni mentors on board"
  },
  {
    "id": "quinceanera-transportation-timing-photos-grand-entrances",
    "slug": "quinceanera-transportation-timing-photos-grand-entrances",
    "title": "Quinceanera Transportation: Timing, Photos, Grand Entrances",
    "excerpt": "Orchestrate church to ballroom transfers with regal cues, cultural respect, and jaw dropping entrances.",
    "content": "It is easy to romanticize quinceanera transportation: timing, photos, grand entrances, but Families spend months on choreography, so transportation must honor every tradition and photo request. Bus2Ride treats every transport storyboard as a live operations document where each promise has an owner and a timestamp. We convert the directional keywords you keep repeating—Quinceanera, Transportation, Timing, Photos—into routing guardrails, staffing ratios, and guest communications. That discipline keeps stakeholders aligned even when celebrity handlers, weather alerts, or late sponsor asks enter the chat at the last minute. By defining success through rider outcomes instead of vehicle specs, the rest of the planning stack becomes calmer and measurably more resilient. The goal is a weekend or single-night move that still feels effortless to guests while your logistics brain knows every variable has a backup.\n\nPlanning begins weeks upstream with discovery calls, forms, and scouting drives anchored around court member timelines, wardrobe change buffers, bilingual MC scripts. We map each traveler persona against the run of show so no one is surprised by attire changes, ADA requirements, or last minute VIP arrivals. Our producers draft layered itineraries that explain who greets whom, which curb is primary versus fallback, and what copy needs to be printed for signage. That documentation lets executives, wedding planners, campus staff, or brand teams sign off quickly because they can see the downstream effect of every choice. We also log no-go rules—the songs that must play, the neighborhoods to avoid, the shots the photographer is chasing—so host energy stays protected. When the planning stack reaches that clarity, even complex quinceanera, cultural, celebration programs feel approachable.\n\nLogistics rehearsal focuses on church curb holds, LED floor protection, bouquet transport cases and the unglamorous tasks that actually preserve timelines. We confirm permits, credential needs, and staging pads with photos, measurements, and contacts so the driver handshake is more than a blind guess. Dispatch receives scenario scripts for weather, traffic gridlock, or celebrity security tweaks, and we mirror those scripts for the host team. Every loop has a dwell budget, fuel plan, restroom strategy, and spare vehicle logic documented in plain English. Because our on-site captains have direct radio or WhatsApp channels with chauffeurs, we can pulse information before a delay becomes a stall. That muscle memory turns potential chaos into small course corrections riders never notice.\n\nAmenities are curated intentionally instead of sprinkled randomly, with the spotlight on tiara stands, floral safe HVAC, mariachi ready audio inputs. We compare rider avatars against cabin layouts to decide where hydration stations, photo props, vow cards, or merch drops should live. Hosts receive a diagram that labels every comfort touch so they know what to hype on the mic, what to protect from overuse, and when to refresh each zone. When a vehicle swap happens, our amenity trunks and digital signage kits move too, which keeps the vibe consistent. We also script how chauffeurs or onboard concierges introduce the upgrades so the spend feels premium rather than gimmicky. Done right, the amenities quietly accelerate boarding, encourage social sharing, and keep the story cohesive from stop to stop.\n\nBudget modeling is transparent because we tie every dollar to a measurable constraint, especially around photo car add ons, overtime allowances for mass blessings, vendor meals. Finance leaders see the decision matrix that compares doing nothing, DIY attempts, or hiring the operator to handle it turnkey. We highlight the costs of failure—injury claims, overtime spirals, missed sponsorship impressions—so approvals feel logical, not emotional. During build-out we log which lines are flexible and which are sacred, making it easier to pivot if the group size or routing changes. Deposits, milestone payments, and gratuity plans are stored in a single tracker to prevent the dreaded text chain of “who still owes what.” With that clarity, stakeholders stay calm even when the scope evolves because they understand the tradeoffs.\n\nExperience design pulls everything together with petal toss kits, drone ready arrival cues, edited highlight films delivered in both languages so guests feel guided instead of herded. We coach emcees, chauffeurs, and onboard crew on language that is inclusive, celebratory, and sensitive to the group’s culture. Live comms go out through SMS, WhatsApp, and QR-enabled microsites so riders always know where to stand, what is next, and who to text for help. Our media team stages photo or video beats that match the narrative arc, whether that is a reveal moment, a toast, or a chill reset. Post-trip surveys gather candid feedback plus testimonials the client can reuse internally, giving the transportation line item long-tail value. When riders feel seen at every touchpoint, the charter becomes part of the story instead of just a shuttle.\n\nIf you want this level of rigor for your own quinceanera transportation: timing, photos, grand entrances, tap the Bus2Ride concierge team and we will adapt the playbook to your city. We can collaborate directly with venues, production partners, hotels, or corporate travel managers and share our dashboards so everyone watches the same KPIs. Send a quick brief to info@bus2ride.com or call (888) 535-2566, and we will workshop route ideas, budgets, and backup plans in the first conversation. From there we lock in the exact fleet mix, staffing model, and amenity set that makes your brand, family, or fan base feel unstoppable.",
    "wordCount": 873,
    "thumbnail_url": "blog/Quinceanera.jpg",
    "published_at": "2025-01-30T12:00:00Z",
    "created_at": "2025-01-30T12:00:00Z",
    "updated_at": "2025-01-30T12:00:00Z",
    "keywords": [
      "quinceanera",
      "cultural",
      "celebration"
    ],
    "introHook": "Families spend months on choreography, so transportation must honor every tradition and photo request.",
    "planningFocus": "court member timelines, wardrobe change buffers, bilingual MC scripts",
    "logisticsFocus": "church curb holds, LED floor protection, bouquet transport cases",
    "amenitiesFocus": "tiara stands, floral safe HVAC, mariachi ready audio inputs",
    "budgetFocus": "photo car add ons, overtime allowances for mass blessings, vendor meals",
    "experienceFocus": "petal toss kits, drone ready arrival cues, edited highlight films delivered in both languages"
  },
  {
    "id": "split-payments-group-budgeting-tools-that-make-it-easy",
    "slug": "split-payments-group-budgeting-tools-that-make-it-easy",
    "title": "Split Payments: Group Budgeting Tools That Make It Easy",
    "excerpt": "Stop chasing Venmo by using structured payment links, contracts, and auto reminders.",
    "content": "It is easy to romanticize split payments: group budgeting tools that make it easy, but Group treasurers burn out when the money tracker lives in a spreadsheet nobody updates. Bus2Ride treats every transport storyboard as a live operations document where each promise has an owner and a timestamp. We convert the directional keywords you keep repeating—Split, Payments, Group, Budgeting—into routing guardrails, staffing ratios, and guest communications. That discipline keeps stakeholders aligned even when celebrity handlers, weather alerts, or late sponsor asks enter the chat at the last minute. By defining success through rider outcomes instead of vehicle specs, the rest of the planning stack becomes calmer and measurably more resilient. The goal is a weekend or single-night move that still feels effortless to guests while your logistics brain knows every variable has a backup.\n\nPlanning begins weeks upstream with discovery calls, forms, and scouting drives anchored around tiered deposit schedules, agreement templates, signer verification workflows. We map each traveler persona against the run of show so no one is surprised by attire changes, ADA requirements, or last minute VIP arrivals. Our producers draft layered itineraries that explain who greets whom, which curb is primary versus fallback, and what copy needs to be printed for signage. That documentation lets executives, wedding planners, campus staff, or brand teams sign off quickly because they can see the downstream effect of every choice. We also log no-go rules—the songs that must play, the neighborhoods to avoid, the shots the photographer is chasing—so host energy stays protected. When the planning stack reaches that clarity, even complex payments, budget, groups programs feel approachable.\n\nLogistics rehearsal focuses on receipt vaults, payment status dashboards, customer service macros and the unglamorous tasks that actually preserve timelines. We confirm permits, credential needs, and staging pads with photos, measurements, and contacts so the driver handshake is more than a blind guess. Dispatch receives scenario scripts for weather, traffic gridlock, or celebrity security tweaks, and we mirror those scripts for the host team. Every loop has a dwell budget, fuel plan, restroom strategy, and spare vehicle logic documented in plain English. Because our on-site captains have direct radio or WhatsApp channels with chauffeurs, we can pulse information before a delay becomes a stall. That muscle memory turns potential chaos into small course corrections riders never notice.\n\nAmenities are curated intentionally instead of sprinkled randomly, with the spotlight on instant confirmation packets, QR codes onboard for tip pooling, branded invoices. We compare rider avatars against cabin layouts to decide where hydration stations, photo props, vow cards, or merch drops should live. Hosts receive a diagram that labels every comfort touch so they know what to hype on the mic, what to protect from overuse, and when to refresh each zone. When a vehicle swap happens, our amenity trunks and digital signage kits move too, which keeps the vibe consistent. We also script how chauffeurs or onboard concierges introduce the upgrades so the spend feels premium rather than gimmicky. Done right, the amenities quietly accelerate boarding, encourage social sharing, and keep the story cohesive from stop to stop.\n\nBudget modeling is transparent because we tie every dollar to a measurable constraint, especially around partial pay options, interest free installments, fail safe funds for no shows. Finance leaders see the decision matrix that compares doing nothing, DIY attempts, or hiring the operator to handle it turnkey. We highlight the costs of failure—injury claims, overtime spirals, missed sponsorship impressions—so approvals feel logical, not emotional. During build-out we log which lines are flexible and which are sacred, making it easier to pivot if the group size or routing changes. Deposits, milestone payments, and gratuity plans are stored in a single tracker to prevent the dreaded text chain of “who still owes what.” With that clarity, stakeholders stay calm even when the scope evolves because they understand the tradeoffs.\n\nExperience design pulls everything together with transparent comms, celebratory notifications when milestones fund, post trip financial reports so guests feel guided instead of herded. We coach emcees, chauffeurs, and onboard crew on language that is inclusive, celebratory, and sensitive to the group’s culture. Live comms go out through SMS, WhatsApp, and QR-enabled microsites so riders always know where to stand, what is next, and who to text for help. Our media team stages photo or video beats that match the narrative arc, whether that is a reveal moment, a toast, or a chill reset. Post-trip surveys gather candid feedback plus testimonials the client can reuse internally, giving the transportation line item long-tail value. When riders feel seen at every touchpoint, the charter becomes part of the story instead of just a shuttle.\n\nIf you want this level of rigor for your own split payments: group budgeting tools that make it easy, tap the Bus2Ride concierge team and we will adapt the playbook to your city. We can collaborate directly with venues, production partners, hotels, or corporate travel managers and share our dashboards so everyone watches the same KPIs. Send a quick brief to info@bus2ride.com or call (888) 535-2566, and we will workshop route ideas, budgets, and backup plans in the first conversation. From there we lock in the exact fleet mix, staffing model, and amenity set that makes your brand, family, or fan base feel unstoppable.",
    "wordCount": 877,
    "thumbnail_url": "blog/Split Payments.jpg",
    "published_at": "2025-01-31T12:00:00Z",
    "created_at": "2025-01-31T12:00:00Z",
    "updated_at": "2025-01-31T12:00:00Z",
    "keywords": [
      "payments",
      "budget",
      "groups"
    ],
    "introHook": "Group treasurers burn out when the money tracker lives in a spreadsheet nobody updates.",
    "planningFocus": "tiered deposit schedules, agreement templates, signer verification workflows",
    "logisticsFocus": "receipt vaults, payment status dashboards, customer service macros",
    "amenitiesFocus": "instant confirmation packets, QR codes onboard for tip pooling, branded invoices",
    "budgetFocus": "partial pay options, interest free installments, fail safe funds for no shows",
    "experienceFocus": "transparent comms, celebratory notifications when milestones fund, post trip financial reports"
  },
  {
    "id": "summer-peak-season-how-to-find-last-minute-availability",
    "slug": "summer-peak-season-how-to-find-last-minute-availability",
    "title": "Summer Peak Season: How to Find Last-Minute Availability",
    "excerpt": "Navigate sold-out calendars with flex fleets, off-peak departures, and multi-city partner networks.",
    "content": "It is easy to romanticize summer peak season: how to find last-minute availability, but Graduations, festivals, and tourism overlap in summer, so waiting costs you both options and leverage. Bus2Ride treats every transport storyboard as a live operations document where each promise has an owner and a timestamp. We convert the directional keywords you keep repeating—Summer, Peak, Season, Find—into routing guardrails, staffing ratios, and guest communications. That discipline keeps stakeholders aligned even when celebrity handlers, weather alerts, or late sponsor asks enter the chat at the last minute. By defining success through rider outcomes instead of vehicle specs, the rest of the planning stack becomes calmer and measurably more resilient. The goal is a weekend or single-night move that still feels effortless to guests while your logistics brain knows every variable has a backup.\n\nPlanning begins weeks upstream with discovery calls, forms, and scouting drives anchored around priority waitlists, rolling hold deposits, daily fleet intel calls. We map each traveler persona against the run of show so no one is surprised by attire changes, ADA requirements, or last minute VIP arrivals. Our producers draft layered itineraries that explain who greets whom, which curb is primary versus fallback, and what copy needs to be printed for signage. That documentation lets executives, wedding planners, campus staff, or brand teams sign off quickly because they can see the downstream effect of every choice. We also log no-go rules—the songs that must play, the neighborhoods to avoid, the shots the photographer is chasing—so host energy stays protected. When the planning stack reaches that clarity, even complex summer, availability, booking programs feel approachable.\n\nLogistics rehearsal focuses on secondary markets, deadhead trades, staggered pickup windows to stretch assets and the unglamorous tasks that actually preserve timelines. We confirm permits, credential needs, and staging pads with photos, measurements, and contacts so the driver handshake is more than a blind guess. Dispatch receives scenario scripts for weather, traffic gridlock, or celebrity security tweaks, and we mirror those scripts for the host team. Every loop has a dwell budget, fuel plan, restroom strategy, and spare vehicle logic documented in plain English. Because our on-site captains have direct radio or WhatsApp channels with chauffeurs, we can pulse information before a delay becomes a stall. That muscle memory turns potential chaos into small course corrections riders never notice.\n\nAmenities are curated intentionally instead of sprinkled randomly, with the spotlight on swap friendly decor kits, portable amenity trunks, fan-friendly hydration bins. We compare rider avatars against cabin layouts to decide where hydration stations, photo props, vow cards, or merch drops should live. Hosts receive a diagram that labels every comfort touch so they know what to hype on the mic, what to protect from overuse, and when to refresh each zone. When a vehicle swap happens, our amenity trunks and digital signage kits move too, which keeps the vibe consistent. We also script how chauffeurs or onboard concierges introduce the upgrades so the spend feels premium rather than gimmicky. Done right, the amenities quietly accelerate boarding, encourage social sharing, and keep the story cohesive from stop to stop.\n\nBudget modeling is transparent because we tie every dollar to a measurable constraint, especially around premium surge allowances, blended fleet packages, cross-market broker fees. Finance leaders see the decision matrix that compares doing nothing, DIY attempts, or hiring the operator to handle it turnkey. We highlight the costs of failure—injury claims, overtime spirals, missed sponsorship impressions—so approvals feel logical, not emotional. During build-out we log which lines are flexible and which are sacred, making it easier to pivot if the group size or routing changes. Deposits, milestone payments, and gratuity plans are stored in a single tracker to prevent the dreaded text chain of “who still owes what.” With that clarity, stakeholders stay calm even when the scope evolves because they understand the tradeoffs.\n\nExperience design pulls everything together with option menus for hosts, transparent scarcity messaging, make good offers when compromises arise so guests feel guided instead of herded. We coach emcees, chauffeurs, and onboard crew on language that is inclusive, celebratory, and sensitive to the group’s culture. Live comms go out through SMS, WhatsApp, and QR-enabled microsites so riders always know where to stand, what is next, and who to text for help. Our media team stages photo or video beats that match the narrative arc, whether that is a reveal moment, a toast, or a chill reset. Post-trip surveys gather candid feedback plus testimonials the client can reuse internally, giving the transportation line item long-tail value. When riders feel seen at every touchpoint, the charter becomes part of the story instead of just a shuttle.\n\nIf you want this level of rigor for your own summer peak season: how to find last-minute availability, tap the Bus2Ride concierge team and we will adapt the playbook to your city. We can collaborate directly with venues, production partners, hotels, or corporate travel managers and share our dashboards so everyone watches the same KPIs. Send a quick brief to info@bus2ride.com or call (888) 535-2566, and we will workshop route ideas, budgets, and backup plans in the first conversation. From there we lock in the exact fleet mix, staffing model, and amenity set that makes your brand, family, or fan base feel unstoppable.",
    "wordCount": 877,
    "thumbnail_url": "blog/Summer.jpg",
    "published_at": "2025-02-01T12:00:00Z",
    "created_at": "2025-02-01T12:00:00Z",
    "updated_at": "2025-02-01T12:00:00Z",
    "keywords": [
      "summer",
      "availability",
      "booking"
    ],
    "introHook": "Graduations, festivals, and tourism overlap in summer, so waiting costs you both options and leverage.",
    "planningFocus": "priority waitlists, rolling hold deposits, daily fleet intel calls",
    "logisticsFocus": "secondary markets, deadhead trades, staggered pickup windows to stretch assets",
    "amenitiesFocus": "swap friendly decor kits, portable amenity trunks, fan-friendly hydration bins",
    "budgetFocus": "premium surge allowances, blended fleet packages, cross-market broker fees",
    "experienceFocus": "option menus for hosts, transparent scarcity messaging, make good offers when compromises arise"
  },
  {
    "id": "wedding-transportation-guide-limo-vs-party-bus-vs-shuttle",
    "slug": "wedding-transportation-guide-limo-vs-party-bus-vs-shuttle",
    "title": "Wedding Transportation Guide: Limo vs Party Bus vs Shuttle",
    "excerpt": "Build layered wedding transportation with separate vibes for couples, VIPs, and guest shuttles.",
    "content": "It is easy to romanticize wedding transportation guide: limo vs party bus vs shuttle, but From rehearsal dinner to sparkler exit, transportation is the only vendor touching every chapter of the weekend. Bus2Ride treats every transport storyboard as a live operations document where each promise has an owner and a timestamp. We convert the directional keywords you keep repeating—Wedding, Transportation, Guide, Limo—into routing guardrails, staffing ratios, and guest communications. That discipline keeps stakeholders aligned even when celebrity handlers, weather alerts, or late sponsor asks enter the chat at the last minute. By defining success through rider outcomes instead of vehicle specs, the rest of the planning stack becomes calmer and measurably more resilient. The goal is a weekend or single-night move that still feels effortless to guests while your logistics brain knows every variable has a backup.\n\nPlanning begins weeks upstream with discovery calls, forms, and scouting drives anchored around timeline weaving, VIP car queues, rain plans that still feel luxe. We map each traveler persona against the run of show so no one is surprised by attire changes, ADA requirements, or last minute VIP arrivals. Our producers draft layered itineraries that explain who greets whom, which curb is primary versus fallback, and what copy needs to be printed for signage. That documentation lets executives, wedding planners, campus staff, or brand teams sign off quickly because they can see the downstream effect of every choice. We also log no-go rules—the songs that must play, the neighborhoods to avoid, the shots the photographer is chasing—so host energy stays protected. When the planning stack reaches that clarity, even complex wedding, transportation, planning programs feel approachable.\n\nLogistics rehearsal focuses on valet coordination, resort loop scripts, load marshals with radios and the unglamorous tasks that actually preserve timelines. We confirm permits, credential needs, and staging pads with photos, measurements, and contacts so the driver handshake is more than a blind guess. Dispatch receives scenario scripts for weather, traffic gridlock, or celebrity security tweaks, and we mirror those scripts for the host team. Every loop has a dwell budget, fuel plan, restroom strategy, and spare vehicle logic documented in plain English. Because our on-site captains have direct radio or WhatsApp channels with chauffeurs, we can pulse information before a delay becomes a stall. That muscle memory turns potential chaos into small course corrections riders never notice.\n\nAmenities are curated intentionally instead of sprinkled randomly, with the spotlight on champagne rituals, vow card stations, climate zones for gowns. We compare rider avatars against cabin layouts to decide where hydration stations, photo props, vow cards, or merch drops should live. Hosts receive a diagram that labels every comfort touch so they know what to hype on the mic, what to protect from overuse, and when to refresh each zone. When a vehicle swap happens, our amenity trunks and digital signage kits move too, which keeps the vibe consistent. We also script how chauffeurs or onboard concierges introduce the upgrades so the spend feels premium rather than gimmicky. Done right, the amenities quietly accelerate boarding, encourage social sharing, and keep the story cohesive from stop to stop.\n\nBudget modeling is transparent because we tie every dollar to a measurable constraint, especially around hybrid fleet bundles, overtime buffers, gratuity envelopes handled by concierge. Finance leaders see the decision matrix that compares doing nothing, DIY attempts, or hiring the operator to handle it turnkey. We highlight the costs of failure—injury claims, overtime spirals, missed sponsorship impressions—so approvals feel logical, not emotional. During build-out we log which lines are flexible and which are sacred, making it easier to pivot if the group size or routing changes. Deposits, milestone payments, and gratuity plans are stored in a single tracker to prevent the dreaded text chain of “who still owes what.” With that clarity, stakeholders stay calm even when the scope evolves because they understand the tradeoffs.\n\nExperience design pulls everything together with storytelling chauffeurs, narrated scenic detours, thank you letters from the couple post honeymoon so guests feel guided instead of herded. We coach emcees, chauffeurs, and onboard crew on language that is inclusive, celebratory, and sensitive to the group’s culture. Live comms go out through SMS, WhatsApp, and QR-enabled microsites so riders always know where to stand, what is next, and who to text for help. Our media team stages photo or video beats that match the narrative arc, whether that is a reveal moment, a toast, or a chill reset. Post-trip surveys gather candid feedback plus testimonials the client can reuse internally, giving the transportation line item long-tail value. When riders feel seen at every touchpoint, the charter becomes part of the story instead of just a shuttle.\n\nIf you want this level of rigor for your own wedding transportation guide: limo vs party bus vs shuttle, tap the Bus2Ride concierge team and we will adapt the playbook to your city. We can collaborate directly with venues, production partners, hotels, or corporate travel managers and share our dashboards so everyone watches the same KPIs. Send a quick brief to info@bus2ride.com or call (888) 535-2566, and we will workshop route ideas, budgets, and backup plans in the first conversation. From there we lock in the exact fleet mix, staffing model, and amenity set that makes your brand, family, or fan base feel unstoppable.",
    "wordCount": 882,
    "thumbnail_url": "blog/Wedding Transportation.jpg",
    "published_at": "2025-02-02T12:00:00Z",
    "created_at": "2025-02-02T12:00:00Z",
    "updated_at": "2025-02-02T12:00:00Z",
    "keywords": [
      "wedding",
      "transportation",
      "planning"
    ],
    "introHook": "From rehearsal dinner to sparkler exit, transportation is the only vendor touching every chapter of the weekend.",
    "planningFocus": "timeline weaving, VIP car queues, rain plans that still feel luxe",
    "logisticsFocus": "valet coordination, resort loop scripts, load marshals with radios",
    "amenitiesFocus": "champagne rituals, vow card stations, climate zones for gowns",
    "budgetFocus": "hybrid fleet bundles, overtime buffers, gratuity envelopes handled by concierge",
    "experienceFocus": "storytelling chauffeurs, narrated scenic detours, thank you letters from the couple post honeymoon"
  }
]